[
  {
    "isOther": false,
    "name": "acc-tcflvffl",
    "phone": "09657445970",
    "phone2": "09895258761",
    "whatsapp": "09646734601",
    "brandName": "brand-1ldf5ik2",
    "countTransactions": 0,
    "countInvoices": 0,
    "finalAmount": {},
    "finalShouldPay": {},
    "finalShouldReceive": {},
    "finalExchangeAmount": {},
    "finalExchangeShouldPay": {},
    "finalExchangeShouldReceive": {},
    "province": "68b6bf0984408c6bf562988e",
    "city": "68b6bf0984408c6bf562988d",
    "address": "address-sc06zuqa",
    "sharedWithTenants": [],
    "creator": "68c3d86084408c6bf5637aec",
    "tenant": "68c3d86084408c6bf5637aea",
    "invoices": [],
    "transactions": [],
    "_id": "68c3fdfc84408c6bf5639a79",
    "deleted": false,
    "createdAt": "2025-09-12T11:03:24.500Z",
    "updatedAt": "2025-09-12T11:03:24.500Z",
    "__v": 0
  },
  {
    "isOther": false,
    "name": "acc-9ws90md2",
    "phone": "09665777435",
    "phone2": "09673583185",
    "whatsapp": "09797677661",
    "brandName": "brand-mz40rmp1",
    "countTransactions": 0,
    "countInvoices": 0,
    "finalAmount": {},
    "finalShouldPay": {},
    "finalShouldReceive": {},
    "finalExchangeAmount": {},
    "finalExchangeShouldPay": {},
    "finalExchangeShouldReceive": {},
    "province": "68b6bf0984408c6bf562988e",
    "city": "68b6bf0984408c6bf562988d",
    "address": "address-ksnn8xs4",
    "sharedWithTenants": [],
    "creator": "68c3d86084408c6bf5637aec",
    "tenant": "68c3d86084408c6bf5637aea",
    "invoices": [],
    "transactions": [],
    "_id": "68c3fe5184408c6bf5639b78",
    "deleted": false,
    "createdAt": "2025-09-12T11:04:49.350Z",
    "updatedAt": "2025-09-12T11:04:49.350Z",
    "__v": 0
  },
  {
    "isOther": false,
    "name": "acc-j60wfnkf",
    "phone": "09780483427",
    "phone2": "09309654519",
    "whatsapp": "09307899678",
    "brandName": "brand-jx167teq",
    "countTransactions": 0,
    "countInvoices": 0,
    "finalAmount": {},
    "finalShouldPay": {},
    "finalShouldReceive": {},
    "finalExchangeAmount": {},
    "finalExchangeShouldPay": {},
    "finalExchangeShouldReceive": {},
    "province": "68b6bf0984408c6bf562988e",
    "city": "68b6bf0984408c6bf562988d",
    "address": "address-e65ggu6r",
    "sharedWithTenants": [],
    "creator": "68c3d86084408c6bf5637aec",
    "tenant": "68c3d86084408c6bf5637aea",
    "invoices": [],
    "transactions": [],
    "_id": "68c3ff0d84408c6bf5639c61",
    "deleted": false,
    "createdAt": "2025-09-12T11:07:57.585Z",
    "updatedAt": "2025-09-12T11:07:57.585Z",
    "__v": 0
  },
  {
    "isOther": false,
    "name": "acc-08scluyd",
    "phone": "09607419875",
    "phone2": "09412662829",
    "whatsapp": "09107948090",
    "brandName": "brand-lmad74me",
    "countTransactions": 0,
    "countInvoices": 0,
    "finalAmount": {},
    "finalShouldPay": {},
    "finalShouldReceive": {},
    "finalExchangeAmount": {},
    "finalExchangeShouldPay": {},
    "finalExchangeShouldReceive": {},
    "province": "68b6bf0984408c6bf562988e",
    "city": "68b6bf0984408c6bf562988d",
    "address": "address-u9hmr7bi",
    "sharedWithTenants": [],
    "creator": "68c3d86084408c6bf5637aec",
    "tenant": "68c3d86084408c6bf5637aea",
    "invoices": [],
    "transactions": [],
    "_id": "68c3ff3484408c6bf5639d79",
    "deleted": false,
    "createdAt": "2025-09-12T11:08:36.741Z",
    "updatedAt": "2025-09-12T11:08:36.741Z",
    "__v": 0
  },
  {
    "isOther": false,
    "name": "acc-imssy8r1",
    "phone": "09726209938",
    "phone2": "09756868775",
    "whatsapp": "09735367519",
    "brandName": "brand-4hv7ti4c",
    "countTransactions": 0,
    "countInvoices": 0,
    "finalAmount": {},
    "finalShouldPay": {},
    "finalShouldReceive": {},
    "finalExchangeAmount": {},
    "finalExchangeShouldPay": {},
    "finalExchangeShouldReceive": {},
    "province": "68b6bf0984408c6bf562988e",
    "city": "68b6bf0984408c6bf562988d",
    "address": "address-5cqbmfn7",
    "sharedWithTenants": [],
    "creator": "68c3d86084408c6bf5637aec",
    "tenant": "68c3d86084408c6bf5637aea",
    "invoices": [],
    "transactions": [],
    "_id": "68c3ffc884408c6bf5639e97",
    "deleted": false,
    "createdAt": "2025-09-12T11:11:04.935Z",
    "updatedAt": "2025-09-12T11:11:04.935Z",
    "__v": 0
  },
  {
    "isOther": false,
    "name": "acc-iunfrwuw",
    "phone": "09277251301",
    "phone2": "09689267205",
    "whatsapp": "09905524585",
    "brandName": "brand-6b226k7f",
    "countTransactions": 0,
    "countInvoices": 0,
    "finalAmount": {},
    "finalShouldPay": {},
    "finalShouldReceive": {},
    "finalExchangeAmount": {},
    "finalExchangeShouldPay": {},
    "finalExchangeShouldReceive": {},
    "province": "68b6bf0984408c6bf562988e",
    "city": "68b6bf0984408c6bf562988d",
    "address": "address-wnp1tq50",
    "sharedWithTenants": [],
    "creator": "68c3d86084408c6bf5637aec",
    "tenant": "68c3d86084408c6bf5637aea",
    "invoices": [],
    "transactions": [],
    "_id": "68c4004284408c6bf5639f92",
    "deleted": false,
    "createdAt": "2025-09-12T11:13:06.993Z",
    "updatedAt": "2025-09-12T11:13:06.993Z",
    "__v": 0
  },
  {
    "isOther": false,
    "name": "acc-gv1fw3a0",
    "phone": "09359939577",
    "phone2": "09327165850",
    "whatsapp": "09302042976",
    "brandName": "brand-l5o6cdyz",
    "countTransactions": 0,
    "countInvoices": 0,
    "finalAmount": {},
    "finalShouldPay": {},
    "finalShouldReceive": {},
    "finalExchangeAmount": {},
    "finalExchangeShouldPay": {},
    "finalExchangeShouldReceive": {},
    "province": "68b6bf0984408c6bf562988e",
    "city": "68b6bf0984408c6bf562988d",
    "address": "address-p504ci6p",
    "sharedWithTenants": [],
    "creator": "68c3d86084408c6bf5637aec",
    "tenant": "68c3d86084408c6bf5637aea",
    "invoices": [],
    "transactions": [],
    "_id": "68c400a584408c6bf563a0a8",
    "deleted": false,
    "createdAt": "2025-09-12T11:14:45.429Z",
    "updatedAt": "2025-09-12T11:14:45.429Z",
    "__v": 0
  },
  {
    "isOther": false,
    "name": "acc-knw9sfge",
    "phone": "09241408688",
    "phone2": "09590532049",
    "whatsapp": "09738242692",
    "brandName": "brand-zpzsbo0p",
    "countTransactions": 0,
    "countInvoices": 0,
    "finalAmount": {},
    "finalShouldPay": {},
    "finalShouldReceive": {},
    "finalExchangeAmount": {},
    "finalExchangeShouldPay": {},
    "finalExchangeShouldReceive": {},
    "province": "68b6bf0984408c6bf562988e",
    "city": "68b6bf0984408c6bf562988d",
    "address": "address-9v18syk9",
    "sharedWithTenants": [],
    "creator": "68c3d86084408c6bf5637aec",
    "tenant": "68c3d86084408c6bf5637aea",
    "invoices": [],
    "transactions": [],
    "_id": "68c4015a84408c6bf563a179",
    "deleted": false,
    "createdAt": "2025-09-12T11:17:46.850Z",
    "updatedAt": "2025-09-12T11:17:46.850Z",
    "__v": 0
  },
  {
    "isOther": false,
    "name": "acc-06198f88",
    "phone": "09233203684",
    "phone2": "09838377745",
    "whatsapp": "09611792592",
    "brandName": "brand-d3d4fib2",
    "countTransactions": 0,
    "countInvoices": 0,
    "finalAmount": {},
    "finalShouldPay": {},
    "finalShouldReceive": {},
    "finalExchangeAmount": {},
    "finalExchangeShouldPay": {},
    "finalExchangeShouldReceive": {},
    "province": "68b6bf0984408c6bf562988e",
    "city": "68b6bf0984408c6bf562988d",
    "address": "address-7w9f98m9",
    "sharedWithTenants": [],
    "creator": "68c3d86084408c6bf5637aec",
    "tenant": "68c3d86084408c6bf5637aea",
    "invoices": [],
    "transactions": [],
    "_id": "68c401d884408c6bf563a280",
    "deleted": false,
    "createdAt": "2025-09-12T11:19:52.463Z",
    "updatedAt": "2025-09-12T11:19:52.463Z",
    "__v": 0
  },
  {
    "isOther": false,
    "name": "acc-ksil66fo",
    "phone": "09949862502",
    "phone2": "09806040553",
    "whatsapp": "09847269516",
    "brandName": "brand-pxapyf0h",
    "countTransactions": 0,
    "countInvoices": 0,
    "finalAmount": {},
    "finalShouldPay": {},
    "finalShouldReceive": {},
    "finalExchangeAmount": {},
    "finalExchangeShouldPay": {},
    "finalExchangeShouldReceive": {},
    "province": "68b6bf0984408c6bf562988e",
    "city": "68b6bf0984408c6bf562988d",
    "address": "address-kcm5nrdu",
    "sharedWithTenants": [],
    "creator": "68c3d86084408c6bf5637aec",
    "tenant": "68c3d86084408c6bf5637aea",
    "invoices": [],
    "transactions": [],
    "_id": "68c4021b84408c6bf563a38e",
    "deleted": false,
    "createdAt": "2025-09-12T11:20:59.304Z",
    "updatedAt": "2025-09-12T11:20:59.304Z",
    "__v": 0
  },
  {
    "isOther": false,
    "name": "acc-a5v52yi5",
    "phone": "09553354983",
    "phone2": "09799891174",
    "whatsapp": "09857934237",
    "brandName": "brand-4pqfqs0r",
    "countTransactions": 0,
    "countInvoices": 0,
    "finalAmount": {},
    "finalShouldPay": {},
    "finalShouldReceive": {},
    "finalExchangeAmount": {},
    "finalExchangeShouldPay": {},
    "finalExchangeShouldReceive": {},
    "province": "68b6bf0984408c6bf562988e",
    "city": "68b6bf0984408c6bf562988d",
    "address": "address-74tskt11",
    "sharedWithTenants": [],
    "creator": "68c3d86084408c6bf5637aec",
    "tenant": "68c3d86084408c6bf5637aea",
    "invoices": [],
    "transactions": [],
    "_id": "68c4030584408c6bf563a485",
    "deleted": false,
    "createdAt": "2025-09-12T11:24:53.104Z",
    "updatedAt": "2025-09-12T11:24:53.104Z",
    "__v": 0
  },
  {
    "isOther": false,
    "name": "acc-798oy13z",
    "phone": "09402988612",
    "phone2": "09597688170",
    "whatsapp": "09262859578",
    "brandName": "brand-hyw1cknd",
    "countTransactions": 0,
    "countInvoices": 0,
    "finalAmount": {},
    "finalShouldPay": {},
    "finalShouldReceive": {},
    "finalExchangeAmount": {},
    "finalExchangeShouldPay": {},
    "finalExchangeShouldReceive": {},
    "province": "68b6bf0984408c6bf562988e",
    "city": "68b6bf0984408c6bf562988d",
    "address": "address-rvto5q4m",
    "sharedWithTenants": [],
    "creator": "68c3d86084408c6bf5637aec",
    "tenant": "68c3d86084408c6bf5637aea",
    "invoices": [],
    "transactions": [],
    "_id": "68c4035484408c6bf563a507",
    "deleted": false,
    "createdAt": "2025-09-12T11:26:12.198Z",
    "updatedAt": "2025-09-12T11:26:12.198Z",
    "__v": 0
  },
  {
    "isOther": false,
    "name": "acc-a8kmlb6n",
    "phone": "09507653147",
    "phone2": "09244830476",
    "whatsapp": "09748093528",
    "brandName": "brand-ecswthl3",
    "countTransactions": 0,
    "countInvoices": 0,
    "finalAmount": {},
    "finalShouldPay": {},
    "finalShouldReceive": {},
    "finalExchangeAmount": {},
    "finalExchangeShouldPay": {},
    "finalExchangeShouldReceive": {},
    "province": "68b6bf0984408c6bf562988e",
    "city": "68b6bf0984408c6bf562988d",
    "address": "address-40hg296k",
    "sharedWithTenants": [],
    "creator": "68c3d86084408c6bf5637aec",
    "tenant": "68c3d86084408c6bf5637aea",
    "invoices": [],
    "transactions": [],
    "_id": "68c405ea84408c6bf563a818",
    "deleted": false,
    "createdAt": "2025-09-12T11:37:14.400Z",
    "updatedAt": "2025-09-12T11:37:14.400Z",
    "__v": 0
  },
  {
    "isOther": false,
    "name": "acc-kwlgzxga",
    "phone": "09966979881",
    "phone2": "09944086981",
    "whatsapp": "09899905056",
    "brandName": "brand-wd3110z5",
    "countTransactions": 0,
    "countInvoices": 0,
    "finalAmount": {},
    "finalShouldPay": {},
    "finalShouldReceive": {},
    "finalExchangeAmount": {},
    "finalExchangeShouldPay": {},
    "finalExchangeShouldReceive": {},
    "province": "68b6bf0984408c6bf562988e",
    "city": "68b6bf0984408c6bf562988d",
    "address": "address-yzx38v5m",
    "sharedWithTenants": [],
    "creator": "68c3d86084408c6bf5637aec",
    "tenant": "68c3d86084408c6bf5637aea",
    "invoices": [],
    "transactions": [],
    "_id": "68c406de84408c6bf563a918",
    "deleted": false,
    "createdAt": "2025-09-12T11:41:18.416Z",
    "updatedAt": "2025-09-12T11:41:18.416Z",
    "__v": 0
  },
  {
    "isOther": false,
    "name": "acc-9iw0y8fp",
    "phone": "09740973082",
    "phone2": "09394060164",
    "whatsapp": "09572009933",
    "brandName": "brand-18uwcd4y",
    "countTransactions": 0,
    "countInvoices": 0,
    "finalAmount": {},
    "finalShouldPay": {},
    "finalShouldReceive": {},
    "finalExchangeAmount": {},
    "finalExchangeShouldPay": {},
    "finalExchangeShouldReceive": {},
    "province": "68b6bf0984408c6bf562988e",
    "city": "68b6bf0984408c6bf562988d",
    "address": "address-ygga529a",
    "sharedWithTenants": [],
    "creator": "68c3d86084408c6bf5637aec",
    "tenant": "68c3d86084408c6bf5637aea",
    "invoices": [],
    "transactions": [],
    "_id": "68c4074884408c6bf563aa03",
    "deleted": false,
    "createdAt": "2025-09-12T11:43:04.033Z",
    "updatedAt": "2025-09-12T11:43:04.033Z",
    "__v": 0
  },
  {
    "isOther": false,
    "name": "acc-7iwevwjf",
    "phone": "09843718723",
    "phone2": "09418225359",
    "whatsapp": "09877171588",
    "brandName": "brand-6w79y2xd",
    "countTransactions": 0,
    "countInvoices": 0,
    "finalAmount": {},
    "finalShouldPay": {},
    "finalShouldReceive": {},
    "finalExchangeAmount": {},
    "finalExchangeShouldPay": {},
    "finalExchangeShouldReceive": {},
    "province": "68b6bf0984408c6bf562988e",
    "city": "68b6bf0984408c6bf562988d",
    "address": "address-k73w7nxw",
    "sharedWithTenants": [],
    "creator": "68c3d86084408c6bf5637aec",
    "tenant": "68c3d86084408c6bf5637aea",
    "invoices": [],
    "transactions": [],
    "_id": "68c407a884408c6bf563aaf0",
    "deleted": false,
    "createdAt": "2025-09-12T11:44:40.240Z",
    "updatedAt": "2025-09-12T11:44:40.240Z",
    "__v": 0
  },
  {
    "isOther": false,
    "name": "acc-f5wkb6un",
    "phone": "09366524804",
    "phone2": "09571564228",
    "whatsapp": "09887742123",
    "brandName": "brand-6z5qe82o",
    "countTransactions": 0,
    "countInvoices": 0,
    "finalAmount": {},
    "finalShouldPay": {},
    "finalShouldReceive": {},
    "finalExchangeAmount": {},
    "finalExchangeShouldPay": {},
    "finalExchangeShouldReceive": {},
    "province": "68b6bf0984408c6bf562988e",
    "city": "68b6bf0984408c6bf562988d",
    "address": "address-9u7vrehh",
    "sharedWithTenants": [],
    "creator": "68c3d86084408c6bf5637aec",
    "tenant": "68c3d86084408c6bf5637aea",
    "invoices": [],
    "transactions": [],
    "_id": "68c4087784408c6bf563ac01",
    "deleted": false,
    "createdAt": "2025-09-12T11:48:07.767Z",
    "updatedAt": "2025-09-12T11:48:07.767Z",
    "__v": 0
  },
  {
    "isOther": false,
    "name": "acc-7ug16xmb",
    "phone": "09882858763",
    "phone2": "09589851901",
    "whatsapp": "09943770824",
    "brandName": "brand-33upzg43",
    "countTransactions": 0,
    "countInvoices": 0,
    "finalAmount": {},
    "finalShouldPay": {},
    "finalShouldReceive": {},
    "finalExchangeAmount": {},
    "finalExchangeShouldPay": {},
    "finalExchangeShouldReceive": {},
    "province": "68b6bf0984408c6bf562988e",
    "city": "68b6bf0984408c6bf562988d",
    "address": "address-uh1a80u5",
    "sharedWithTenants": [],
    "creator": "68c3d86084408c6bf5637aec",
    "tenant": "68c3d86084408c6bf5637aea",
    "invoices": [],
    "transactions": [],
    "_id": "68c408c084408c6bf563acc1",
    "deleted": false,
    "createdAt": "2025-09-12T11:49:20.595Z",
    "updatedAt": "2025-09-12T11:49:20.595Z",
    "__v": 0
  },
  {
    "isOther": false,
    "name": "acc-ikp2iidl",
    "phone": "09178910694",
    "phone2": "09712433555",
    "whatsapp": "09775521134",
    "brandName": "brand-vg3eycat",
    "countTransactions": 0,
    "countInvoices": 0,
    "finalAmount": {},
    "finalShouldPay": {},
    "finalShouldReceive": {},
    "finalExchangeAmount": {},
    "finalExchangeShouldPay": {},
    "finalExchangeShouldReceive": {},
    "province": "68b6bf0984408c6bf562988e",
    "city": "68b6bf0984408c6bf562988d",
    "address": "address-7o0sboo8",
    "sharedWithTenants": [],
    "creator": "68c3d86084408c6bf5637aec",
    "tenant": "68c3d86084408c6bf5637aea",
    "invoices": [],
    "transactions": [],
    "_id": "68c408ef84408c6bf563adca",
    "deleted": false,
    "createdAt": "2025-09-12T11:50:07.744Z",
    "updatedAt": "2025-09-12T11:50:07.744Z",
    "__v": 0
  },
  {
    "isOther": false,
    "name": "acc-fe7gxjvp",
    "phone": "09129636229",
    "phone2": "09801675805",
    "whatsapp": "09360013468",
    "brandName": "brand-0hu66o6f",
    "countTransactions": 0,
    "countInvoices": 0,
    "finalAmount": {},
    "finalShouldPay": {},
    "finalShouldReceive": {},
    "finalExchangeAmount": {},
    "finalExchangeShouldPay": {},
    "finalExchangeShouldReceive": {},
    "province": "68b6bf0984408c6bf562988e",
    "city": "68b6bf0984408c6bf562988d",
    "address": "address-fwh5qvuy",
    "sharedWithTenants": [],
    "creator": "68c3d86084408c6bf5637aec",
    "tenant": "68c3d86084408c6bf5637aea",
    "invoices": [],
    "transactions": [],
    "_id": "68c409ef84408c6bf563aec1",
    "deleted": false,
    "createdAt": "2025-09-12T11:54:23.123Z",
    "updatedAt": "2025-09-12T11:54:23.123Z",
    "__v": 0
  },
  {
    "isOther": false,
    "name": "acc-gz7iqcgo",
    "phone": "09807430465",
    "phone2": "09788017019",
    "whatsapp": "09437692563",
    "brandName": "brand-up6l67r8",
    "countTransactions": 0,
    "countInvoices": 0,
    "finalAmount": {},
    "finalShouldPay": {},
    "finalShouldReceive": {},
    "finalExchangeAmount": {},
    "finalExchangeShouldPay": {},
    "finalExchangeShouldReceive": {},
    "province": "68b6bf0984408c6bf562988e",
    "city": "68b6bf0984408c6bf562988d",
    "address": "address-5rserpdw",
    "sharedWithTenants": [],
    "creator": "68c3d86084408c6bf5637aec",
    "tenant": "68c3d86084408c6bf5637aea",
    "invoices": [],
    "transactions": [],
    "_id": "68c40b0184408c6bf563afb4",
    "deleted": false,
    "createdAt": "2025-09-12T11:58:57.900Z",
    "updatedAt": "2025-09-12T11:58:57.900Z",
    "__v": 0
  },
  {
    "isOther": false,
    "name": "acc-7jxcgysn",
    "phone": "09486919742",
    "phone2": "09593822751",
    "whatsapp": "09347902965",
    "brandName": "brand-5s9i047f",
    "countTransactions": 0,
    "countInvoices": 0,
    "finalAmount": {},
    "finalShouldPay": {},
    "finalShouldReceive": {},
    "finalExchangeAmount": {},
    "finalExchangeShouldPay": {},
    "finalExchangeShouldReceive": {},
    "province": "68b6bf0984408c6bf562988e",
    "city": "68b6bf0984408c6bf562988d",
    "address": "address-19zj5kzh",
    "sharedWithTenants": [],
    "creator": "68c3d86084408c6bf5637aec",
    "tenant": "68c3d86084408c6bf5637aea",
    "invoices": [],
    "transactions": [],
    "_id": "68c40b3f84408c6bf563b087",
    "deleted": false,
    "createdAt": "2025-09-12T11:59:59.400Z",
    "updatedAt": "2025-09-12T11:59:59.400Z",
    "__v": 0
  },
  {
    "isOther": false,
    "name": "acc-4dy4rglq",
    "phone": "09259631605",
    "phone2": "09182705685",
    "whatsapp": "09893538814",
    "brandName": "brand-xnxl4x2u",
    "countTransactions": 0,
    "countInvoices": 0,
    "finalAmount": {},
    "finalShouldPay": {},
    "finalShouldReceive": {},
    "finalExchangeAmount": {},
    "finalExchangeShouldPay": {},
    "finalExchangeShouldReceive": {},
    "province": "68b6bf0984408c6bf562988e",
    "city": "68b6bf0984408c6bf562988d",
    "address": "address-ke9j6f9m",
    "sharedWithTenants": [],
    "creator": "68c3d86084408c6bf5637aec",
    "tenant": "68c3d86084408c6bf5637aea",
    "invoices": [],
    "transactions": [],
    "_id": "68c40bf484408c6bf563b166",
    "deleted": false,
    "createdAt": "2025-09-12T12:03:00.218Z",
    "updatedAt": "2025-09-12T12:03:00.218Z",
    "__v": 0
  },
  {
    "isOther": false,
    "name": "acc-zd3yqz9u",
    "phone": "09206362151",
    "phone2": "09187484417",
    "whatsapp": "09864556194",
    "brandName": "brand-55a2lvi7",
    "countTransactions": 0,
    "countInvoices": 0,
    "finalAmount": {},
    "finalShouldPay": {},
    "finalShouldReceive": {},
    "finalExchangeAmount": {},
    "finalExchangeShouldPay": {},
    "finalExchangeShouldReceive": {},
    "province": "68b6bf0984408c6bf562988e",
    "city": "68b6bf0984408c6bf562988d",
    "address": "address-5qqqtgbd",
    "sharedWithTenants": [],
    "creator": "68c3d86084408c6bf5637aec",
    "tenant": "68c3d86084408c6bf5637aea",
    "invoices": [],
    "transactions": [],
    "_id": "68c40ced84408c6bf563b249",
    "deleted": false,
    "createdAt": "2025-09-12T12:07:09.074Z",
    "updatedAt": "2025-09-12T12:07:09.074Z",
    "__v": 0
  },
  {
    "isOther": false,
    "name": "acc-jm1a950c",
    "phone": "09871254823",
    "phone2": "09355012692",
    "whatsapp": "09112146579",
    "brandName": "brand-u0hmi816",
    "countTransactions": 0,
    "countInvoices": 0,
    "finalAmount": {},
    "finalShouldPay": {},
    "finalShouldReceive": {},
    "finalExchangeAmount": {},
    "finalExchangeShouldPay": {},
    "finalExchangeShouldReceive": {},
    "province": "68b6bf0984408c6bf562988e",
    "city": "68b6bf0984408c6bf562988d",
    "address": "address-b4wayu7y",
    "sharedWithTenants": [],
    "creator": "68c3d86084408c6bf5637aec",
    "tenant": "68c3d86084408c6bf5637aea",
    "invoices": [],
    "transactions": [],
    "_id": "68c40db284408c6bf563b329",
    "deleted": false,
    "createdAt": "2025-09-12T12:10:26.520Z",
    "updatedAt": "2025-09-12T12:10:26.520Z",
    "__v": 0
  },
  {
    "isOther": false,
    "name": "acc-l8dyrto2",
    "phone": "09489332458",
    "phone2": "09671217987",
    "whatsapp": "09363928262",
    "brandName": "brand-tpd7yx70",
    "countTransactions": 0,
    "countInvoices": 0,
    "finalAmount": {},
    "finalShouldPay": {},
    "finalShouldReceive": {},
    "finalExchangeAmount": {},
    "finalExchangeShouldPay": {},
    "finalExchangeShouldReceive": {},
    "province": "68b6bf0984408c6bf562988e",
    "city": "68b6bf0984408c6bf562988d",
    "address": "address-hi9mw22f",
    "sharedWithTenants": [],
    "creator": "68c3d86084408c6bf5637aec",
    "tenant": "68c3d86084408c6bf5637aea",
    "invoices": [],
    "transactions": [],
    "_id": "68c40e8684408c6bf563b43c",
    "deleted": false,
    "createdAt": "2025-09-12T12:13:58.332Z",
    "updatedAt": "2025-09-12T12:13:58.332Z",
    "__v": 0
  },
  {
    "isOther": false,
    "name": "acc-kvi7gpi2",
    "phone": "09250769694",
    "phone2": "09752316639",
    "whatsapp": "09394352046",
    "brandName": "brand-lr5znx64",
    "countTransactions": 0,
    "countInvoices": 0,
    "finalAmount": {},
    "finalShouldPay": {},
    "finalShouldReceive": {},
    "finalExchangeAmount": {},
    "finalExchangeShouldPay": {},
    "finalExchangeShouldReceive": {},
    "province": "68b6bf0984408c6bf562988e",
    "city": "68b6bf0984408c6bf562988d",
    "address": "address-xcqq4bsp",
    "sharedWithTenants": [],
    "creator": "68c3d86084408c6bf5637aec",
    "tenant": "68c3d86084408c6bf5637aea",
    "invoices": [],
    "transactions": [],
    "_id": "68c40f9384408c6bf563b52b",
    "deleted": false,
    "createdAt": "2025-09-12T12:18:27.491Z",
    "updatedAt": "2025-09-12T12:18:27.491Z",
    "__v": 0
  },
  {
    "isOther": false,
    "name": "acc-w7nigtsd",
    "phone": "09237280032",
    "phone2": "09149823637",
    "whatsapp": "09876702190",
    "brandName": "brand-ueman7k5",
    "countTransactions": 0,
    "countInvoices": 0,
    "finalAmount": {},
    "finalShouldPay": {},
    "finalShouldReceive": {},
    "finalExchangeAmount": {},
    "finalExchangeShouldPay": {},
    "finalExchangeShouldReceive": {},
    "province": "68b6bf0984408c6bf562988e",
    "city": "68b6bf0984408c6bf562988d",
    "address": "address-nuaavpqi",
    "sharedWithTenants": [],
    "creator": "68c3d86084408c6bf5637aec",
    "tenant": "68c3d86084408c6bf5637aea",
    "invoices": [],
    "transactions": [],
    "_id": "68c4108884408c6bf563b605",
    "deleted": false,
    "createdAt": "2025-09-12T12:22:32.417Z",
    "updatedAt": "2025-09-12T12:22:32.417Z",
    "__v": 0
  },
  {
    "isOther": false,
    "name": "acc-ruwp7q1i",
    "phone": "09663630794",
    "phone2": "09418615384",
    "whatsapp": "09455933321",
    "brandName": "brand-xc4vfpmo",
    "countTransactions": 0,
    "countInvoices": 0,
    "finalAmount": {},
    "finalShouldPay": {},
    "finalShouldReceive": {},
    "finalExchangeAmount": {},
    "finalExchangeShouldPay": {},
    "finalExchangeShouldReceive": {},
    "province": "68b6bf0984408c6bf562988e",
    "city": "68b6bf0984408c6bf562988d",
    "address": "address-oh96kpz0",
    "sharedWithTenants": [],
    "creator": "68c3d86084408c6bf5637aec",
    "tenant": "68c3d86084408c6bf5637aea",
    "invoices": [],
    "transactions": [],
    "_id": "68c4116184408c6bf563b6e7",
    "deleted": false,
    "createdAt": "2025-09-12T12:26:09.705Z",
    "updatedAt": "2025-09-12T12:26:09.705Z",
    "__v": 0
  },
  {
    "isOther": false,
    "name": "acc-x9yz89hj",
    "phone": "09987296606",
    "phone2": "09535142847",
    "whatsapp": "09815722462",
    "brandName": "brand-8nkcc1ah",
    "countTransactions": 0,
    "countInvoices": 0,
    "finalAmount": {},
    "finalShouldPay": {},
    "finalShouldReceive": {},
    "finalExchangeAmount": {},
    "finalExchangeShouldPay": {},
    "finalExchangeShouldReceive": {},
    "province": "68b6bf0984408c6bf562988e",
    "city": "68b6bf0984408c6bf562988d",
    "address": "address-zwq5rcsv",
    "sharedWithTenants": [],
    "creator": "68c3d86084408c6bf5637aec",
    "tenant": "68c3d86084408c6bf5637aea",
    "invoices": [],
    "transactions": [],
    "_id": "68c4118384408c6bf563b7e2",
    "deleted": false,
    "createdAt": "2025-09-12T12:26:43.512Z",
    "updatedAt": "2025-09-12T12:26:43.512Z",
    "__v": 0
  },
  {
    "isOther": false,
    "name": "acc-vpizqews",
    "phone": "09537314193",
    "phone2": "09459357681",
    "whatsapp": "09330654832",
    "brandName": "brand-o1tu46w6",
    "countTransactions": 0,
    "countInvoices": 0,
    "finalAmount": {},
    "finalShouldPay": {},
    "finalShouldReceive": {},
    "finalExchangeAmount": {},
    "finalExchangeShouldPay": {},
    "finalExchangeShouldReceive": {},
    "province": "68b6bf0984408c6bf562988e",
    "city": "68b6bf0984408c6bf562988d",
    "address": "address-7gep4tk1",
    "sharedWithTenants": [],
    "creator": "68c3d86084408c6bf5637aec",
    "tenant": "68c3d86084408c6bf5637aea",
    "invoices": [],
    "transactions": [],
    "_id": "68c412ce84408c6bf563b8ee",
    "deleted": false,
    "createdAt": "2025-09-12T12:32:14.126Z",
    "updatedAt": "2025-09-12T12:32:14.126Z",
    "__v": 0
  },
  {
    "isOther": false,
    "name": "acc-2fjusy90",
    "phone": "09107282109",
    "phone2": "09985761060",
    "whatsapp": "09592682702",
    "brandName": "brand-0qp4wxxs",
    "countTransactions": 0,
    "countInvoices": 0,
    "finalAmount": {},
    "finalShouldPay": {},
    "finalShouldReceive": {},
    "finalExchangeAmount": {},
    "finalExchangeShouldPay": {},
    "finalExchangeShouldReceive": {},
    "province": "68b6bf0984408c6bf562988e",
    "city": "68b6bf0984408c6bf562988d",
    "address": "address-yvjr2r00",
    "sharedWithTenants": [],
    "creator": "68c3d86084408c6bf5637aec",
    "tenant": "68c3d86084408c6bf5637aea",
    "invoices": [],
    "transactions": [],
    "_id": "68c412fb84408c6bf563ba23",
    "deleted": false,
    "createdAt": "2025-09-12T12:32:59.208Z",
    "updatedAt": "2025-09-12T12:32:59.208Z",
    "__v": 0
  },
  {
    "isOther": false,
    "name": "acc-hoho2p9z",
    "phone": "09128618233",
    "phone2": "09909765311",
    "whatsapp": "09394067863",
    "brandName": "brand-7w4z8rzo",
    "countTransactions": 0,
    "countInvoices": 0,
    "finalAmount": {},
    "finalShouldPay": {},
    "finalShouldReceive": {},
    "finalExchangeAmount": {},
    "finalExchangeShouldPay": {},
    "finalExchangeShouldReceive": {},
    "province": "68b6bf0984408c6bf562988e",
    "city": "68b6bf0984408c6bf562988d",
    "address": "address-tnmddrld",
    "sharedWithTenants": [],
    "creator": "68c3d86084408c6bf5637aec",
    "tenant": "68c3d86084408c6bf5637aea",
    "invoices": [],
    "transactions": [],
    "_id": "68c4158f84408c6bf563bac4",
    "deleted": false,
    "createdAt": "2025-09-12T12:43:59.444Z",
    "updatedAt": "2025-09-12T12:43:59.444Z",
    "__v": 0
  },
  {
    "isOther": false,
    "name": "acc-8wih3ddr",
    "phone": "09928237567",
    "phone2": "09141100286",
    "whatsapp": "09605807902",
    "brandName": "brand-ro5kk3fn",
    "countTransactions": 0,
    "countInvoices": 0,
    "finalAmount": {},
    "finalShouldPay": {},
    "finalShouldReceive": {},
    "finalExchangeAmount": {},
    "finalExchangeShouldPay": {},
    "finalExchangeShouldReceive": {},
    "province": "68b6bf0984408c6bf562988e",
    "city": "68b6bf0984408c6bf562988d",
    "address": "address-8hiokq4x",
    "sharedWithTenants": [],
    "creator": "68c5bdd784408c6bf563bb9b",
    "tenant": "68c5bdd484408c6bf563bb87",
    "invoices": [],
    "transactions": [],
    "_id": "68c5bddc84408c6bf563bc00",
    "deleted": false,
    "createdAt": "2025-09-13T18:54:20.589Z",
    "updatedAt": "2025-09-13T18:54:20.589Z",
    "__v": 0
  },
  {
    "isOther": false,
    "name": "acc-2nhjkgci",
    "phone": "09425112806",
    "phone2": "09755257285",
    "whatsapp": "09519257188",
    "brandName": "brand-w7b4mlle",
    "countTransactions": 0,
    "countInvoices": 0,
    "finalAmount": {},
    "finalShouldPay": {},
    "finalShouldReceive": {},
    "finalExchangeAmount": {},
    "finalExchangeShouldPay": {},
    "finalExchangeShouldReceive": {},
    "province": "68b6bf0984408c6bf562988e",
    "city": "68b6bf0984408c6bf562988d",
    "address": "address-jtbfuab9",
    "sharedWithTenants": [],
    "creator": "68c5bdd784408c6bf563bb9b",
    "tenant": "68c5bdd484408c6bf563bb87",
    "invoices": [],
    "transactions": [],
    "_id": "68c5c85784408c6bf563bd09",
    "deleted": false,
    "createdAt": "2025-09-13T19:39:03.490Z",
    "updatedAt": "2025-09-13T19:39:03.490Z",
    "__v": 0
  },
  {
    "isOther": false,
    "name": "acc-cq2l8h8p",
    "phone": "09632502113",
    "phone2": "09683280856",
    "whatsapp": "09710251944",
    "brandName": "brand-o9zvvhoa",
    "countTransactions": 0,
    "countInvoices": 0,
    "finalAmount": {},
    "finalShouldPay": {},
    "finalShouldReceive": {},
    "finalExchangeAmount": {},
    "finalExchangeShouldPay": {},
    "finalExchangeShouldReceive": {},
    "province": "68b6bf0984408c6bf562988e",
    "city": "68b6bf0984408c6bf562988d",
    "address": "address-ocmu4o6e",
    "sharedWithTenants": [],
    "creator": "68c5bdd784408c6bf563bb9b",
    "tenant": "68c5bdd484408c6bf563bb87",
    "invoices": [],
    "transactions": [],
    "_id": "68c5c90d84408c6bf563bd46",
    "deleted": false,
    "createdAt": "2025-09-13T19:42:05.796Z",
    "updatedAt": "2025-09-13T19:42:05.796Z",
    "__v": 0
  },
  {
    "isOther": false,
    "name": "acc-gmzazu28",
    "phone": "09247248784",
    "phone2": "09678925187",
    "whatsapp": "09401640157",
    "brandName": "brand-a8drf44t",
    "countTransactions": 0,
    "countInvoices": 0,
    "finalAmount": {},
    "finalShouldPay": {},
    "finalShouldReceive": {},
    "finalExchangeAmount": {},
    "finalExchangeShouldPay": {},
    "finalExchangeShouldReceive": {},
    "province": "68b6bf0984408c6bf562988e",
    "city": "68b6bf0984408c6bf562988d",
    "address": "address-tvzi1ky5",
    "sharedWithTenants": [],
    "creator": "68c5bdd784408c6bf563bb9b",
    "tenant": "68c5bdd484408c6bf563bb87",
    "invoices": [],
    "transactions": [],
    "_id": "68c5c98984408c6bf563bdf4",
    "deleted": false,
    "createdAt": "2025-09-13T19:44:09.793Z",
    "updatedAt": "2025-09-13T19:44:09.793Z",
    "__v": 0
  },
  {
    "isOther": false,
    "name": "acc-33wn2usl",
    "phone": "09182136689",
    "phone2": "09561593593",
    "whatsapp": "09734289400",
    "brandName": "brand-vjnmsfdd",
    "countTransactions": 0,
    "countInvoices": 0,
    "finalAmount": {},
    "finalShouldPay": {},
    "finalShouldReceive": {},
    "finalExchangeAmount": {},
    "finalExchangeShouldPay": {},
    "finalExchangeShouldReceive": {},
    "province": "68b6bf0984408c6bf562988e",
    "city": "68b6bf0984408c6bf562988d",
    "address": "address-y21qgnwt",
    "sharedWithTenants": [],
    "creator": "68c5bdd784408c6bf563bb9b",
    "tenant": "68c5bdd484408c6bf563bb87",
    "invoices": [],
    "transactions": [],
    "_id": "68c5c9f484408c6bf563beaf",
    "deleted": false,
    "createdAt": "2025-09-13T19:45:56.604Z",
    "updatedAt": "2025-09-13T19:45:56.604Z",
    "__v": 0
  },
  {
    "isOther": false,
    "name": "acc-t84us4xs",
    "phone": "09770471467",
    "phone2": "09728871443",
    "whatsapp": "09761503532",
    "brandName": "brand-oasf8bq8",
    "countTransactions": 0,
    "countInvoices": 0,
    "finalAmount": {},
    "finalShouldPay": {},
    "finalShouldReceive": {},
    "finalExchangeAmount": {},
    "finalExchangeShouldPay": {},
    "finalExchangeShouldReceive": {},
    "province": "68b6bf0984408c6bf562988e",
    "city": "68b6bf0984408c6bf562988d",
    "address": "address-cfqsj9xf",
    "sharedWithTenants": [],
    "creator": "68c5bdd784408c6bf563bb9b",
    "tenant": "68c5bdd484408c6bf563bb87",
    "invoices": [],
    "transactions": [],
    "_id": "68c5cada84408c6bf563bfec",
    "deleted": false,
    "createdAt": "2025-09-13T19:49:46.660Z",
    "updatedAt": "2025-09-13T19:49:46.660Z",
    "__v": 0
  },
  {
    "isOther": false,
    "name": "acc-djemcxbv",
    "phone": "09681605260",
    "phone2": "09954877144",
    "whatsapp": "09853372331",
    "brandName": "brand-4l8a4j7s",
    "countTransactions": 0,
    "countInvoices": 0,
    "finalAmount": {},
    "finalShouldPay": {},
    "finalShouldReceive": {},
    "finalExchangeAmount": {},
    "finalExchangeShouldPay": {},
    "finalExchangeShouldReceive": {},
    "province": "68b6bf0984408c6bf562988e",
    "city": "68b6bf0984408c6bf562988d",
    "address": "address-b5s980w4",
    "sharedWithTenants": [],
    "creator": "68c5bdd784408c6bf563bb9b",
    "tenant": "68c5bdd484408c6bf563bb87",
    "invoices": [],
    "transactions": [],
    "_id": "68c5cb7284408c6bf563c10b",
    "deleted": false,
    "createdAt": "2025-09-13T19:52:18.798Z",
    "updatedAt": "2025-09-13T19:52:18.798Z",
    "__v": 0
  },
  {
    "isOther": false,
    "name": "acc-95e0pfao",
    "phone": "09115304295",
    "phone2": "09386153368",
    "whatsapp": "09893618831",
    "brandName": "brand-yqaquno9",
    "countTransactions": 0,
    "countInvoices": 0,
    "finalAmount": {},
    "finalShouldPay": {},
    "finalShouldReceive": {},
    "finalExchangeAmount": {},
    "finalExchangeShouldPay": {},
    "finalExchangeShouldReceive": {},
    "province": "68b6bf0984408c6bf562988e",
    "city": "68b6bf0984408c6bf562988d",
    "address": "address-mbszznay",
    "sharedWithTenants": [],
    "creator": "68c5bdd784408c6bf563bb9b",
    "tenant": "68c5bdd484408c6bf563bb87",
    "invoices": [],
    "transactions": [],
    "_id": "68c5cc8184408c6bf563c220",
    "deleted": false,
    "createdAt": "2025-09-13T19:56:49.402Z",
    "updatedAt": "2025-09-13T19:56:49.402Z",
    "__v": 0
  },
  {
    "isOther": false,
    "name": "acc-8zv9q25y",
    "phone": "09471766721",
    "phone2": "09858605835",
    "whatsapp": "09449819515",
    "brandName": "brand-04zwn9a7",
    "countTransactions": 0,
    "countInvoices": 0,
    "finalAmount": {},
    "finalShouldPay": {},
    "finalShouldReceive": {},
    "finalExchangeAmount": {},
    "finalExchangeShouldPay": {},
    "finalExchangeShouldReceive": {},
    "province": "68b6bf0984408c6bf562988e",
    "city": "68b6bf0984408c6bf562988d",
    "address": "address-0b73c054",
    "sharedWithTenants": [],
    "creator": "68c5bdd784408c6bf563bb9b",
    "tenant": "68c5bdd484408c6bf563bb87",
    "invoices": [],
    "transactions": [],
    "_id": "68c5cc9f84408c6bf563c2fb",
    "deleted": false,
    "createdAt": "2025-09-13T19:57:19.703Z",
    "updatedAt": "2025-09-13T19:57:19.703Z",
    "__v": 0
  },
  {
    "isOther": false,
    "name": "acc-x9kr1saz",
    "phone": "09997835735",
    "phone2": "09421172091",
    "whatsapp": "09522750625",
    "brandName": "brand-s9hih0x7",
    "countTransactions": 0,
    "countInvoices": 0,
    "finalAmount": {},
    "finalShouldPay": {},
    "finalShouldReceive": {},
    "finalExchangeAmount": {},
    "finalExchangeShouldPay": {},
    "finalExchangeShouldReceive": {},
    "province": "68b6bf0984408c6bf562988e",
    "city": "68b6bf0984408c6bf562988d",
    "address": "address-ix5koh6b",
    "sharedWithTenants": [],
    "creator": "68c5bdd784408c6bf563bb9b",
    "tenant": "68c5bdd484408c6bf563bb87",
    "invoices": [],
    "transactions": [],
    "_id": "68c5cd8484408c6bf563c44e",
    "deleted": false,
    "createdAt": "2025-09-13T20:01:08.195Z",
    "updatedAt": "2025-09-13T20:01:08.195Z",
    "__v": 0
  },
  {
    "isOther": false,
    "name": "acc-opm8j183",
    "phone": "09236695611",
    "phone2": "09376835894",
    "whatsapp": "09913060103",
    "brandName": "brand-kmyzvb5h",
    "countTransactions": 0,
    "countInvoices": 0,
    "finalAmount": {},
    "finalShouldPay": {},
    "finalShouldReceive": {},
    "finalExchangeAmount": {},
    "finalExchangeShouldPay": {},
    "finalExchangeShouldReceive": {},
    "province": "68b6bf0984408c6bf562988e",
    "city": "68b6bf0984408c6bf562988d",
    "address": "address-tmgphq8g",
    "sharedWithTenants": [],
    "creator": "68c5bdd784408c6bf563bb9b",
    "tenant": "68c5bdd484408c6bf563bb87",
    "invoices": [],
    "transactions": [],
    "_id": "68c5ce4f84408c6bf563c528",
    "deleted": false,
    "createdAt": "2025-09-13T20:04:31.904Z",
    "updatedAt": "2025-09-13T20:04:31.904Z",
    "__v": 0
  },
  {
    "isOther": false,
    "name": "acc-axeh50rs",
    "phone": "09395418067",
    "phone2": "09864950222",
    "whatsapp": "09422067455",
    "brandName": "brand-dux9o0dw",
    "countTransactions": 0,
    "countInvoices": 0,
    "finalAmount": {},
    "finalShouldPay": {},
    "finalShouldReceive": {},
    "finalExchangeAmount": {},
    "finalExchangeShouldPay": {},
    "finalExchangeShouldReceive": {},
    "province": "68b6bf0984408c6bf562988e",
    "city": "68b6bf0984408c6bf562988d",
    "address": "address-ogyj50wn",
    "sharedWithTenants": [],
    "creator": "68c5bdd784408c6bf563bb9b",
    "tenant": "68c5bdd484408c6bf563bb87",
    "invoices": [],
    "transactions": [],
    "_id": "68c5ce5e84408c6bf563c679",
    "deleted": false,
    "createdAt": "2025-09-13T20:04:46.618Z",
    "updatedAt": "2025-09-13T20:04:46.618Z",
    "__v": 0
  },
  {
    "isOther": false,
    "name": "acc-x3m1tgnn",
    "phone": "09600026924",
    "phone2": "09707246817",
    "whatsapp": "09726278943",
    "brandName": "brand-k4f60r2r",
    "countTransactions": 0,
    "countInvoices": 0,
    "finalAmount": {},
    "finalShouldPay": {},
    "finalShouldReceive": {},
    "finalExchangeAmount": {},
    "finalExchangeShouldPay": {},
    "finalExchangeShouldReceive": {},
    "province": "68b6bf0984408c6bf562988e",
    "city": "68b6bf0984408c6bf562988d",
    "address": "address-722advso",
    "sharedWithTenants": [],
    "creator": "68c5bdd784408c6bf563bb9b",
    "tenant": "68c5bdd484408c6bf563bb87",
    "invoices": [],
    "transactions": [],
    "_id": "68c5ce8284408c6bf563c795",
    "deleted": false,
    "createdAt": "2025-09-13T20:05:22.994Z",
    "updatedAt": "2025-09-13T20:05:22.994Z",
    "__v": 0
  },
  {
    "isOther": false,
    "name": "acc-vdvpxaqa",
    "phone": "09705842260",
    "phone2": "09996151329",
    "whatsapp": "09641066458",
    "brandName": "brand-678kklhd",
    "countTransactions": 0,
    "countInvoices": 0,
    "finalAmount": {},
    "finalShouldPay": {},
    "finalShouldReceive": {},
    "finalExchangeAmount": {},
    "finalExchangeShouldPay": {},
    "finalExchangeShouldReceive": {},
    "province": "68b6bf0984408c6bf562988e",
    "city": "68b6bf0984408c6bf562988d",
    "address": "address-al12ok78",
    "sharedWithTenants": [],
    "creator": "68c5bdd784408c6bf563bb9b",
    "tenant": "68c5bdd484408c6bf563bb87",
    "invoices": [],
    "transactions": [],
    "_id": "68c5ce9284408c6bf563c855",
    "deleted": false,
    "createdAt": "2025-09-13T20:05:38.093Z",
    "updatedAt": "2025-09-13T20:05:38.093Z",
    "__v": 0
  },
  {
    "isOther": false,
    "name": "acc-9flx2cg8",
    "phone": "09593536778",
    "phone2": "09140775096",
    "whatsapp": "09963217068",
    "brandName": "brand-sgv849sj",
    "countTransactions": 0,
    "countInvoices": 0,
    "finalAmount": {},
    "finalShouldPay": {},
    "finalShouldReceive": {},
    "finalExchangeAmount": {},
    "finalExchangeShouldPay": {},
    "finalExchangeShouldReceive": {},
    "province": "68b6bf0984408c6bf562988e",
    "city": "68b6bf0984408c6bf562988d",
    "address": "address-1w4cqfgz",
    "sharedWithTenants": [],
    "creator": "68c5bdd784408c6bf563bb9b",
    "tenant": "68c5bdd484408c6bf563bb87",
    "invoices": [],
    "transactions": [],
    "_id": "68c5cf3584408c6bf563c999",
    "deleted": false,
    "createdAt": "2025-09-13T20:08:21.790Z",
    "updatedAt": "2025-09-13T20:08:21.790Z",
    "__v": 0
  },
  {
    "isOther": false,
    "name": "acc-8z0aj6wr",
    "phone": "09526448920",
    "phone2": "09456675999",
    "whatsapp": "09410151566",
    "brandName": "brand-k3x1b7lc",
    "countTransactions": 0,
    "countInvoices": 0,
    "finalAmount": {},
    "finalShouldPay": {},
    "finalShouldReceive": {},
    "finalExchangeAmount": {},
    "finalExchangeShouldPay": {},
    "finalExchangeShouldReceive": {},
    "province": "68b6bf0984408c6bf562988e",
    "city": "68b6bf0984408c6bf562988d",
    "address": "address-kj8d1v4x",
    "sharedWithTenants": [],
    "creator": "68c5bdd784408c6bf563bb9b",
    "tenant": "68c5bdd484408c6bf563bb87",
    "invoices": [],
    "transactions": [],
    "_id": "68c5cf8e84408c6bf563cacb",
    "deleted": false,
    "createdAt": "2025-09-13T20:09:50.391Z",
    "updatedAt": "2025-09-13T20:09:50.391Z",
    "__v": 0
  },
  {
    "isOther": false,
    "name": "acc-jb947ylh",
    "phone": "09609079932",
    "phone2": "09687522530",
    "whatsapp": "09844647611",
    "brandName": "brand-duk7z9gh",
    "countTransactions": 0,
    "countInvoices": 0,
    "finalAmount": {},
    "finalShouldPay": {},
    "finalShouldReceive": {},
    "finalExchangeAmount": {},
    "finalExchangeShouldPay": {},
    "finalExchangeShouldReceive": {},
    "province": "68b6bf0984408c6bf562988e",
    "city": "68b6bf0984408c6bf562988d",
    "address": "address-138timsz",
    "sharedWithTenants": [],
    "creator": "68c5bdd784408c6bf563bb9b",
    "tenant": "68c5bdd484408c6bf563bb87",
    "invoices": [],
    "transactions": [],
    "_id": "68c5d0ca84408c6bf563cbdb",
    "deleted": false,
    "createdAt": "2025-09-13T20:15:06.390Z",
    "updatedAt": "2025-09-13T20:15:06.390Z",
    "__v": 0
  },
  {
    "isOther": false,
    "name": "acc-tltx4rj4",
    "phone": "09464448118",
    "phone2": "09532101636",
    "whatsapp": "09289546722",
    "brandName": "brand-7ukcj0ae",
    "countTransactions": 0,
    "countInvoices": 0,
    "finalAmount": {},
    "finalShouldPay": {},
    "finalShouldReceive": {},
    "finalExchangeAmount": {},
    "finalExchangeShouldPay": {},
    "finalExchangeShouldReceive": {},
    "province": "68b6bf0984408c6bf562988e",
    "city": "68b6bf0984408c6bf562988d",
    "address": "address-bqa9afat",
    "sharedWithTenants": [],
    "creator": "68c5bdd784408c6bf563bb9b",
    "tenant": "68c5bdd484408c6bf563bb87",
    "invoices": [],
    "transactions": [],
    "_id": "68c5d1a684408c6bf563cce4",
    "deleted": false,
    "createdAt": "2025-09-13T20:18:46.414Z",
    "updatedAt": "2025-09-13T20:18:46.414Z",
    "__v": 0
  },
  {
    "isOther": false,
    "name": "acc-z9x9vmze",
    "phone": "09850514122",
    "phone2": "09543199971",
    "whatsapp": "09604318662",
    "brandName": "brand-0z9wr85k",
    "countTransactions": 0,
    "countInvoices": 0,
    "finalAmount": {},
    "finalShouldPay": {},
    "finalShouldReceive": {},
    "finalExchangeAmount": {},
    "finalExchangeShouldPay": {},
    "finalExchangeShouldReceive": {},
    "province": "68b6bf0984408c6bf562988e",
    "city": "68b6bf0984408c6bf562988d",
    "address": "address-3vk4ob6l",
    "sharedWithTenants": [],
    "creator": "68c5bdd784408c6bf563bb9b",
    "tenant": "68c5bdd484408c6bf563bb87",
    "invoices": [],
    "transactions": [],
    "_id": "68c5d23584408c6bf563cdec",
    "deleted": false,
    "createdAt": "2025-09-13T20:21:09.931Z",
    "updatedAt": "2025-09-13T20:21:09.931Z",
    "__v": 0
  },
  {
    "isOther": false,
    "name": "acc-77m77c7v",
    "phone": "09676086225",
    "phone2": "09578443938",
    "whatsapp": "09619445504",
    "brandName": "brand-7d9artn1",
    "countTransactions": 0,
    "countInvoices": 0,
    "finalAmount": {},
    "finalShouldPay": {},
    "finalShouldReceive": {},
    "finalExchangeAmount": {},
    "finalExchangeShouldPay": {},
    "finalExchangeShouldReceive": {},
    "province": "68b6bf0984408c6bf562988e",
    "city": "68b6bf0984408c6bf562988d",
    "address": "address-n543t0g3",
    "sharedWithTenants": [],
    "creator": "68c5bdd784408c6bf563bb9b",
    "tenant": "68c5bdd484408c6bf563bb87",
    "invoices": [],
    "transactions": [],
    "_id": "68c5d2b284408c6bf563cf30",
    "deleted": false,
    "createdAt": "2025-09-13T20:23:14.034Z",
    "updatedAt": "2025-09-13T20:23:14.034Z",
    "__v": 0
  },
  {
    "isOther": false,
    "name": "acc-wx6ws26z",
    "phone": "09902436359",
    "phone2": "09955115197",
    "whatsapp": "09348749060",
    "brandName": "brand-fdgaytco",
    "countTransactions": 0,
    "countInvoices": 0,
    "finalAmount": {},
    "finalShouldPay": {},
    "finalShouldReceive": {},
    "finalExchangeAmount": {},
    "finalExchangeShouldPay": {},
    "finalExchangeShouldReceive": {},
    "province": "68b6bf0984408c6bf562988e",
    "city": "68b6bf0984408c6bf562988d",
    "address": "address-vzfndrrs",
    "sharedWithTenants": [],
    "creator": "68c5bdd784408c6bf563bb9b",
    "tenant": "68c5bdd484408c6bf563bb87",
    "invoices": [],
    "transactions": [],
    "_id": "68c5d2f384408c6bf563d04f",
    "deleted": false,
    "createdAt": "2025-09-13T20:24:19.094Z",
    "updatedAt": "2025-09-13T20:24:19.094Z",
    "__v": 0
  },
  {
    "isOther": false,
    "name": "acc-kbvj6hfk",
    "phone": "09334574219",
    "phone2": "09551520666",
    "whatsapp": "09438795689",
    "brandName": "brand-3lr69en4",
    "countTransactions": 0,
    "countInvoices": 0,
    "finalAmount": {},
    "finalShouldPay": {},
    "finalShouldReceive": {},
    "finalExchangeAmount": {},
    "finalExchangeShouldPay": {},
    "finalExchangeShouldReceive": {},
    "province": "68b6bf0984408c6bf562988e",
    "city": "68b6bf0984408c6bf562988d",
    "address": "address-znttoq8e",
    "sharedWithTenants": [],
    "creator": "68c5bdd784408c6bf563bb9b",
    "tenant": "68c5bdd484408c6bf563bb87",
    "invoices": [],
    "transactions": [],
    "_id": "68c5d37d84408c6bf563d193",
    "deleted": false,
    "createdAt": "2025-09-13T20:26:37.716Z",
    "updatedAt": "2025-09-13T20:26:37.716Z",
    "__v": 0
  },
  {
    "isOther": false,
    "name": "acc-9yfc5f7e",
    "phone": "09833704951",
    "phone2": "09976630793",
    "whatsapp": "09202572237",
    "brandName": "brand-2kgr5gj0",
    "countTransactions": 0,
    "countInvoices": 0,
    "finalAmount": {},
    "finalShouldPay": {},
    "finalShouldReceive": {},
    "finalExchangeAmount": {},
    "finalExchangeShouldPay": {},
    "finalExchangeShouldReceive": {},
    "province": "68b6bf0984408c6bf562988e",
    "city": "68b6bf0984408c6bf562988d",
    "address": "address-hmsom8z8",
    "sharedWithTenants": [],
    "creator": "68c5bdd784408c6bf563bb9b",
    "tenant": "68c5bdd484408c6bf563bb87",
    "invoices": [],
    "transactions": [],
    "_id": "68c5d43684408c6bf563d275",
    "deleted": false,
    "createdAt": "2025-09-13T20:29:42.401Z",
    "updatedAt": "2025-09-13T20:29:42.401Z",
    "__v": 0
  },
  {
    "isOther": false,
    "name": "acc-t9qq1ixi",
    "phone": "09774876985",
    "phone2": "09818454621",
    "whatsapp": "09201957571",
    "brandName": "brand-k7s6p0lw",
    "countTransactions": 0,
    "countInvoices": 0,
    "finalAmount": {},
    "finalShouldPay": {},
    "finalShouldReceive": {},
    "finalExchangeAmount": {},
    "finalExchangeShouldPay": {},
    "finalExchangeShouldReceive": {},
    "province": "68b6bf0984408c6bf562988e",
    "city": "68b6bf0984408c6bf562988d",
    "address": "address-manc0y4h",
    "sharedWithTenants": [],
    "creator": "68c5bdd784408c6bf563bb9b",
    "tenant": "68c5bdd484408c6bf563bb87",
    "invoices": [],
    "transactions": [],
    "_id": "68c5d4f884408c6bf563d3eb",
    "deleted": false,
    "createdAt": "2025-09-13T20:32:56.208Z",
    "updatedAt": "2025-09-13T20:32:56.208Z",
    "__v": 0
  },
  {
    "isOther": false,
    "name": "acc-01i5tdtr",
    "phone": "09915400987",
    "phone2": "09910952138",
    "whatsapp": "09797361912",
    "brandName": "brand-ztf8cyll",
    "countTransactions": 0,
    "countInvoices": 0,
    "finalAmount": {},
    "finalShouldPay": {},
    "finalShouldReceive": {},
    "finalExchangeAmount": {},
    "finalExchangeShouldPay": {},
    "finalExchangeShouldReceive": {},
    "province": "68b6bf0984408c6bf562988e",
    "city": "68b6bf0984408c6bf562988d",
    "address": "address-1brquaip",
    "sharedWithTenants": [],
    "creator": "68c5bdd784408c6bf563bb9b",
    "tenant": "68c5bdd484408c6bf563bb87",
    "invoices": [],
    "transactions": [],
    "_id": "68c7624b289355d669c182c8",
    "deleted": false,
    "createdAt": "2025-09-15T00:48:11.393Z",
    "updatedAt": "2025-09-15T00:48:11.393Z",
    "__v": 0
  },
  {
    "isOther": false,
    "name": "acc-jk9jibiw",
    "phone": "09534467368",
    "phone2": "09795809909",
    "whatsapp": "09848615923",
    "brandName": "brand-plbw2a9u",
    "countTransactions": 0,
    "countInvoices": 0,
    "finalAmount": {},
    "finalShouldPay": {},
    "finalShouldReceive": {},
    "finalExchangeAmount": {},
    "finalExchangeShouldPay": {},
    "finalExchangeShouldReceive": {},
    "province": "68b6bf0984408c6bf562988e",
    "city": "68b6bf0984408c6bf562988d",
    "address": "address-gzj4arvp",
    "sharedWithTenants": [],
    "creator": "68c5bdd784408c6bf563bb9b",
    "tenant": "68c5bdd484408c6bf563bb87",
    "invoices": [],
    "transactions": [],
    "_id": "68c7a5a7289355d669c183d9",
    "deleted": false,
    "createdAt": "2025-09-15T05:35:35.396Z",
    "updatedAt": "2025-09-15T05:35:35.396Z",
    "__v": 0
  },
  {
    "isOther": false,
    "name": "acc-bnnlpye9",
    "phone": "09846261877",
    "phone2": "09736030173",
    "whatsapp": "09566841591",
    "brandName": "brand-5o65v129",
    "countTransactions": 0,
    "countInvoices": 0,
    "finalAmount": {},
    "finalShouldPay": {},
    "finalShouldReceive": {},
    "finalExchangeAmount": {},
    "finalExchangeShouldPay": {},
    "finalExchangeShouldReceive": {},
    "province": "68b6bf0984408c6bf562988e",
    "city": "68b6bf0984408c6bf562988d",
    "address": "address-56kb90dy",
    "sharedWithTenants": [],
    "creator": "68c5bdd784408c6bf563bb9b",
    "tenant": "68c5bdd484408c6bf563bb87",
    "invoices": [],
    "transactions": [],
    "_id": "68c7a63a289355d669c184f0",
    "deleted": false,
    "createdAt": "2025-09-15T05:38:02.227Z",
    "updatedAt": "2025-09-15T05:38:02.227Z",
    "__v": 0
  },
  {
    "isOther": false,
    "name": "acc-6r0b91dg",
    "phone": "09222844133",
    "phone2": "09545218635",
    "whatsapp": "09265367438",
    "brandName": "brand-arvolj7n",
    "countTransactions": 0,
    "countInvoices": 0,
    "finalAmount": {},
    "finalShouldPay": {},
    "finalShouldReceive": {},
    "finalExchangeAmount": {},
    "finalExchangeShouldPay": {},
    "finalExchangeShouldReceive": {},
    "province": "68b6bf0984408c6bf562988e",
    "city": "68b6bf0984408c6bf562988d",
    "address": "address-71ur9l0t",
    "sharedWithTenants": [],
    "creator": "68c5bdd784408c6bf563bb9b",
    "tenant": "68c5bdd484408c6bf563bb87",
    "invoices": [],
    "transactions": [],
    "_id": "68c7a866289355d669c1866d",
    "deleted": false,
    "createdAt": "2025-09-15T05:47:18.791Z",
    "updatedAt": "2025-09-15T05:47:18.791Z",
    "__v": 0
  },
  {
    "isOther": false,
    "name": "acc-ognsq57o",
    "phone": "09313402399",
    "phone2": "09127317479",
    "whatsapp": "09458911641",
    "brandName": "brand-ltxhm1xu",
    "countTransactions": 0,
    "countInvoices": 0,
    "finalAmount": {},
    "finalShouldPay": {},
    "finalShouldReceive": {},
    "finalExchangeAmount": {},
    "finalExchangeShouldPay": {},
    "finalExchangeShouldReceive": {},
    "province": "68b6bf0984408c6bf562988e",
    "city": "68b6bf0984408c6bf562988d",
    "address": "address-9rag9ec2",
    "sharedWithTenants": [],
    "creator": "68c5bdd784408c6bf563bb9b",
    "tenant": "68c5bdd484408c6bf563bb87",
    "invoices": [],
    "transactions": [],
    "_id": "68c7a920289355d669c18772",
    "deleted": false,
    "createdAt": "2025-09-15T05:50:24.593Z",
    "updatedAt": "2025-09-15T05:50:24.593Z",
    "__v": 0
  },
  {
    "isOther": false,
    "name": "acc-4vfo536b",
    "phone": "09147987442",
    "phone2": "09466253594",
    "whatsapp": "09578766976",
    "brandName": "brand-yjzes6zj",
    "countTransactions": 0,
    "countInvoices": 0,
    "finalAmount": {},
    "finalShouldPay": {},
    "finalShouldReceive": {},
    "finalExchangeAmount": {},
    "finalExchangeShouldPay": {},
    "finalExchangeShouldReceive": {},
    "province": "68b6bf0984408c6bf562988e",
    "city": "68b6bf0984408c6bf562988d",
    "address": "address-qs2y95ci",
    "sharedWithTenants": [],
    "creator": "68c5bdd784408c6bf563bb9b",
    "tenant": "68c5bdd484408c6bf563bb87",
    "invoices": [],
    "transactions": [],
    "_id": "68c7a97c289355d669c18898",
    "deleted": false,
    "createdAt": "2025-09-15T05:51:56.315Z",
    "updatedAt": "2025-09-15T05:51:56.315Z",
    "__v": 0
  },
  {
    "isOther": false,
    "name": "acc-ez7bbjlb",
    "phone": "09981066236",
    "phone2": "09725802198",
    "whatsapp": "09129416708",
    "brandName": "brand-xgf7t2cu",
    "countTransactions": 0,
    "countInvoices": 0,
    "finalAmount": {},
    "finalShouldPay": {},
    "finalShouldReceive": {},
    "finalExchangeAmount": {},
    "finalExchangeShouldPay": {},
    "finalExchangeShouldReceive": {},
    "province": "68b6bf0984408c6bf562988e",
    "city": "68b6bf0984408c6bf562988d",
    "address": "address-ftf3kniw",
    "sharedWithTenants": [],
    "creator": "68c5bdd784408c6bf563bb9b",
    "tenant": "68c5bdd484408c6bf563bb87",
    "invoices": [],
    "transactions": [],
    "_id": "68c7a9a7289355d669c189da",
    "deleted": false,
    "createdAt": "2025-09-15T05:52:39.095Z",
    "updatedAt": "2025-09-15T05:52:39.095Z",
    "__v": 0
  },
  {
    "isOther": false,
    "name": "acc-igfq036q",
    "phone": "09368143940",
    "phone2": "09436976694",
    "whatsapp": "09538815370",
    "brandName": "brand-a4zflakh",
    "countTransactions": 0,
    "countInvoices": 0,
    "finalAmount": {},
    "finalShouldPay": {},
    "finalShouldReceive": {},
    "finalExchangeAmount": {},
    "finalExchangeShouldPay": {},
    "finalExchangeShouldReceive": {},
    "province": "68b6bf0984408c6bf562988e",
    "city": "68b6bf0984408c6bf562988d",
    "address": "address-an3vgz1v",
    "sharedWithTenants": [],
    "creator": "68c5bdd784408c6bf563bb9b",
    "tenant": "68c5bdd484408c6bf563bb87",
    "invoices": [],
    "transactions": [],
    "_id": "68c7ae46289355d669c18b0d",
    "deleted": false,
    "createdAt": "2025-09-15T06:12:22.006Z",
    "updatedAt": "2025-09-15T06:12:22.006Z",
    "__v": 0
  },
  {
    "isOther": false,
    "name": "acc-re413g1n",
    "phone": "09117011651",
    "phone2": "09931951301",
    "whatsapp": "09775805630",
    "brandName": "brand-hv1378cm",
    "countTransactions": 0,
    "countInvoices": 0,
    "finalAmount": {},
    "finalShouldPay": {},
    "finalShouldReceive": {},
    "finalExchangeAmount": {},
    "finalExchangeShouldPay": {},
    "finalExchangeShouldReceive": {},
    "province": "68b6bf0984408c6bf562988e",
    "city": "68b6bf0984408c6bf562988d",
    "address": "address-cd1z3p2m",
    "sharedWithTenants": [],
    "creator": "68c5bdd784408c6bf563bb9b",
    "tenant": "68c5bdd484408c6bf563bb87",
    "invoices": [],
    "transactions": [],
    "_id": "68c7b026289355d669c18ca2",
    "deleted": false,
    "createdAt": "2025-09-15T06:20:22.547Z",
    "updatedAt": "2025-09-15T06:20:22.547Z",
    "__v": 0
  },
  {
    "isOther": false,
    "name": "acc-gbx4mna6",
    "phone": "09962157147",
    "phone2": "09531266182",
    "whatsapp": "09686415987",
    "brandName": "brand-y3or6kk3",
    "countTransactions": 0,
    "countInvoices": 0,
    "finalAmount": {},
    "finalShouldPay": {},
    "finalShouldReceive": {},
    "finalExchangeAmount": {},
    "finalExchangeShouldPay": {},
    "finalExchangeShouldReceive": {},
    "province": "68b6bf0984408c6bf562988e",
    "city": "68b6bf0984408c6bf562988d",
    "address": "address-z2zmu4ag",
    "sharedWithTenants": [],
    "creator": "68c5bdd784408c6bf563bb9b",
    "tenant": "68c5bdd484408c6bf563bb87",
    "invoices": [],
    "transactions": [],
    "_id": "68c7bb70289355d669c18e13",
    "deleted": false,
    "createdAt": "2025-09-15T07:08:32.497Z",
    "updatedAt": "2025-09-15T07:08:32.497Z",
    "__v": 0
  },
  {
    "isOther": false,
    "name": "acc-gu01k20r",
    "phone": "09507563561",
    "phone2": "09605885294",
    "whatsapp": "09374065680",
    "brandName": "brand-bzm9mkza",
    "countTransactions": 0,
    "countInvoices": 0,
    "finalAmount": {},
    "finalShouldPay": {},
    "finalShouldReceive": {},
    "finalExchangeAmount": {},
    "finalExchangeShouldPay": {},
    "finalExchangeShouldReceive": {},
    "province": "68b6bf0984408c6bf562988e",
    "city": "68b6bf0984408c6bf562988d",
    "address": "address-nr2g5zre",
    "sharedWithTenants": [],
    "creator": "68c5bdd784408c6bf563bb9b",
    "tenant": "68c5bdd484408c6bf563bb87",
    "invoices": [],
    "transactions": [],
    "_id": "68c7bc7a289355d669c18f63",
    "deleted": false,
    "createdAt": "2025-09-15T07:12:58.912Z",
    "updatedAt": "2025-09-15T07:12:58.912Z",
    "__v": 0
  },
  {
    "isOther": false,
    "name": "acc-tr71y9c0",
    "phone": "09222491915",
    "phone2": "09405910390",
    "whatsapp": "09139449713",
    "brandName": "brand-17tr4mj3",
    "countTransactions": 0,
    "countInvoices": 0,
    "finalAmount": {},
    "finalShouldPay": {},
    "finalShouldReceive": {},
    "finalExchangeAmount": {},
    "finalExchangeShouldPay": {},
    "finalExchangeShouldReceive": {},
    "province": "68b6bf0984408c6bf562988e",
    "city": "68b6bf0984408c6bf562988d",
    "address": "address-ueavvmtr",
    "sharedWithTenants": [],
    "creator": "68c5bdd784408c6bf563bb9b",
    "tenant": "68c5bdd484408c6bf563bb87",
    "invoices": [],
    "transactions": [],
    "_id": "68c7c614289355d669c190dc",
    "deleted": false,
    "createdAt": "2025-09-15T07:53:56.788Z",
    "updatedAt": "2025-09-15T07:53:56.788Z",
    "__v": 0
  },
  {
    "isOther": false,
    "name": "acc-w6nxogcb",
    "phone": "09566134028",
    "phone2": "09465201502",
    "whatsapp": "09421264828",
    "brandName": "brand-l57c08i3",
    "countTransactions": 0,
    "countInvoices": 0,
    "finalAmount": {},
    "finalShouldPay": {},
    "finalShouldReceive": {},
    "finalExchangeAmount": {},
    "finalExchangeShouldPay": {},
    "finalExchangeShouldReceive": {},
    "province": "68b6bf0984408c6bf562988e",
    "city": "68b6bf0984408c6bf562988d",
    "address": "address-nbj2fhmy",
    "sharedWithTenants": [],
    "creator": "68c5bdd784408c6bf563bb9b",
    "tenant": "68c5bdd484408c6bf563bb87",
    "invoices": [],
    "transactions": [],
    "_id": "68c7c68e289355d669c19246",
    "deleted": false,
    "createdAt": "2025-09-15T07:55:58.453Z",
    "updatedAt": "2025-09-15T07:55:58.453Z",
    "__v": 0
  },
  {
    "isOther": false,
    "name": "acc-0mijct2y",
    "phone": "09229205008",
    "phone2": "09242683704",
    "whatsapp": "09579670344",
    "brandName": "brand-ngl9d7f8",
    "countTransactions": 0,
    "countInvoices": 0,
    "finalAmount": {},
    "finalShouldPay": {},
    "finalShouldReceive": {},
    "finalExchangeAmount": {},
    "finalExchangeShouldPay": {},
    "finalExchangeShouldReceive": {},
    "province": "68b6bf0984408c6bf562988e",
    "city": "68b6bf0984408c6bf562988d",
    "address": "address-0jsdfohl",
    "sharedWithTenants": [],
    "creator": "68c5bdd784408c6bf563bb9b",
    "tenant": "68c5bdd484408c6bf563bb87",
    "invoices": [],
    "transactions": [],
    "_id": "68c7c951289355d669c193bb",
    "deleted": false,
    "createdAt": "2025-09-15T08:07:45.257Z",
    "updatedAt": "2025-09-15T08:07:45.257Z",
    "__v": 0
  },
  {
    "isOther": false,
    "name": "acc-y1kqgv3z",
    "phone": "09206266107",
    "phone2": "09796894340",
    "whatsapp": "09846311378",
    "brandName": "brand-zxkf12jr",
    "countTransactions": 0,
    "countInvoices": 0,
    "finalAmount": {},
    "finalShouldPay": {},
    "finalShouldReceive": {},
    "finalExchangeAmount": {},
    "finalExchangeShouldPay": {},
    "finalExchangeShouldReceive": {},
    "province": "68b6bf0984408c6bf562988e",
    "city": "68b6bf0984408c6bf562988d",
    "address": "address-af5toas3",
    "sharedWithTenants": [],
    "creator": "68c5bdd784408c6bf563bb9b",
    "tenant": "68c5bdd484408c6bf563bb87",
    "invoices": [],
    "transactions": [],
    "_id": "68c7caac289355d669c1952e",
    "deleted": false,
    "createdAt": "2025-09-15T08:13:32.875Z",
    "updatedAt": "2025-09-15T08:13:32.875Z",
    "__v": 0
  },
  {
    "isOther": false,
    "name": "acc-hv3l71xe",
    "phone": "09421514043",
    "phone2": "09600524310",
    "whatsapp": "09442884724",
    "brandName": "brand-e3xo67ip",
    "countTransactions": 0,
    "countInvoices": 0,
    "finalAmount": {},
    "finalShouldPay": {},
    "finalShouldReceive": {},
    "finalExchangeAmount": {},
    "finalExchangeShouldPay": {},
    "finalExchangeShouldReceive": {},
    "province": "68b6bf0984408c6bf562988e",
    "city": "68b6bf0984408c6bf562988d",
    "address": "address-arexmihr",
    "sharedWithTenants": [],
    "creator": "68c5bdd784408c6bf563bb9b",
    "tenant": "68c5bdd484408c6bf563bb87",
    "invoices": [],
    "transactions": [],
    "_id": "68c7cb1a289355d669c19678",
    "deleted": false,
    "createdAt": "2025-09-15T08:15:22.913Z",
    "updatedAt": "2025-09-15T08:15:22.913Z",
    "__v": 0
  },
  {
    "isOther": false,
    "name": "acc-4rg85vwj",
    "phone": "09629989182",
    "phone2": "09724672795",
    "whatsapp": "09392026782",
    "brandName": "brand-av6uy9jx",
    "countTransactions": 0,
    "countInvoices": 0,
    "finalAmount": {},
    "finalShouldPay": {},
    "finalShouldReceive": {},
    "finalExchangeAmount": {},
    "finalExchangeShouldPay": {},
    "finalExchangeShouldReceive": {},
    "province": "68b6bf0984408c6bf562988e",
    "city": "68b6bf0984408c6bf562988d",
    "address": "address-m0iibd5o",
    "sharedWithTenants": [],
    "creator": "68c5bdd784408c6bf563bb9b",
    "tenant": "68c5bdd484408c6bf563bb87",
    "invoices": [],
    "transactions": [],
    "_id": "68c7ccce289355d669c197ec",
    "deleted": false,
    "createdAt": "2025-09-15T08:22:38.688Z",
    "updatedAt": "2025-09-15T08:22:38.688Z",
    "__v": 0
  },
  {
    "isOther": false,
    "name": "acc-v66to41n",
    "phone": "09250234644",
    "phone2": "09424707221",
    "whatsapp": "09882367449",
    "brandName": "brand-rkpsjc3z",
    "countTransactions": 0,
    "countInvoices": 0,
    "finalAmount": {},
    "finalShouldPay": {},
    "finalShouldReceive": {},
    "finalExchangeAmount": {},
    "finalExchangeShouldPay": {},
    "finalExchangeShouldReceive": {},
    "province": "68b6bf0984408c6bf562988e",
    "city": "68b6bf0984408c6bf562988d",
    "address": "address-l1lm0lr3",
    "sharedWithTenants": [],
    "creator": "68c5bdd784408c6bf563bb9b",
    "tenant": "68c5bdd484408c6bf563bb87",
    "invoices": [],
    "transactions": [],
    "_id": "68c7cd05289355d669c19968",
    "deleted": false,
    "createdAt": "2025-09-15T08:23:33.566Z",
    "updatedAt": "2025-09-15T08:23:33.566Z",
    "__v": 0
  },
  {
    "isOther": false,
    "name": "acc-hwln70n3",
    "phone": "09153679210",
    "phone2": "09827039405",
    "whatsapp": "09699918302",
    "brandName": "brand-ruh82t8o",
    "countTransactions": 0,
    "countInvoices": 0,
    "finalAmount": {},
    "finalShouldPay": {},
    "finalShouldReceive": {},
    "finalExchangeAmount": {},
    "finalExchangeShouldPay": {},
    "finalExchangeShouldReceive": {},
    "province": "68b6bf0984408c6bf562988e",
    "city": "68b6bf0984408c6bf562988d",
    "address": "address-ydaxss9s",
    "sharedWithTenants": [],
    "creator": "68c5bdd784408c6bf563bb9b",
    "tenant": "68c5bdd484408c6bf563bb87",
    "invoices": [],
    "transactions": [],
    "_id": "68c7cd6e289355d669c19ab4",
    "deleted": false,
    "createdAt": "2025-09-15T08:25:18.665Z",
    "updatedAt": "2025-09-15T08:25:18.665Z",
    "__v": 0
  },
  {
    "isOther": false,
    "name": "acc-1271qxec",
    "phone": "09446064744",
    "phone2": "09906652985",
    "whatsapp": "09345861698",
    "brandName": "brand-4r4b14qu",
    "countTransactions": 0,
    "countInvoices": 0,
    "finalAmount": {},
    "finalShouldPay": {},
    "finalShouldReceive": {},
    "finalExchangeAmount": {},
    "finalExchangeShouldPay": {},
    "finalExchangeShouldReceive": {},
    "province": "68b6bf0984408c6bf562988e",
    "city": "68b6bf0984408c6bf562988d",
    "address": "address-9bvno42s",
    "sharedWithTenants": [],
    "creator": "68c5bdd784408c6bf563bb9b",
    "tenant": "68c5bdd484408c6bf563bb87",
    "invoices": [],
    "transactions": [],
    "_id": "68c7ced1289355d669c19c16",
    "deleted": false,
    "createdAt": "2025-09-15T08:31:13.389Z",
    "updatedAt": "2025-09-15T08:31:13.389Z",
    "__v": 0
  },
  {
    "isOther": false,
    "name": "acc-6vrvvj4h",
    "phone": "09739473412",
    "phone2": "09483364234",
    "whatsapp": "09540925332",
    "brandName": "brand-bqralzft",
    "countTransactions": 0,
    "countInvoices": 0,
    "finalAmount": {},
    "finalShouldPay": {},
    "finalShouldReceive": {},
    "finalExchangeAmount": {},
    "finalExchangeShouldPay": {},
    "finalExchangeShouldReceive": {},
    "province": "68b6bf0984408c6bf562988e",
    "city": "68b6bf0984408c6bf562988d",
    "address": "address-gtumg2cc",
    "sharedWithTenants": [],
    "creator": "68c5bdd784408c6bf563bb9b",
    "tenant": "68c5bdd484408c6bf563bb87",
    "invoices": [],
    "transactions": [],
    "_id": "68c7ceec289355d669c19d7e",
    "deleted": false,
    "createdAt": "2025-09-15T08:31:40.099Z",
    "updatedAt": "2025-09-15T08:31:40.099Z",
    "__v": 0
  },
  {
    "isOther": false,
    "name": "acc-rs2ml0j2",
    "phone": "09433996441",
    "phone2": "09405468538",
    "whatsapp": "09251781240",
    "brandName": "brand-lvhi2jqa",
    "countTransactions": 0,
    "countInvoices": 0,
    "finalAmount": {},
    "finalShouldPay": {},
    "finalShouldReceive": {},
    "finalExchangeAmount": {},
    "finalExchangeShouldPay": {},
    "finalExchangeShouldReceive": {},
    "province": "68b6bf0984408c6bf562988e",
    "city": "68b6bf0984408c6bf562988d",
    "address": "address-vuhqwbzg",
    "sharedWithTenants": [],
    "creator": "68c5bdd784408c6bf563bb9b",
    "tenant": "68c5bdd484408c6bf563bb87",
    "invoices": [],
    "transactions": [],
    "_id": "68c7d09f289355d669c19f06",
    "deleted": false,
    "createdAt": "2025-09-15T08:38:55.061Z",
    "updatedAt": "2025-09-15T08:38:55.061Z",
    "__v": 0
  },
  {
    "isOther": false,
    "name": "acc-gp3brrt3",
    "phone": "09201638693",
    "phone2": "09115408910",
    "whatsapp": "09485282591",
    "brandName": "brand-15f1f1oo",
    "countTransactions": 0,
    "countInvoices": 0,
    "finalAmount": {},
    "finalShouldPay": {},
    "finalShouldReceive": {},
    "finalExchangeAmount": {},
    "finalExchangeShouldPay": {},
    "finalExchangeShouldReceive": {},
    "province": "68b6bf0984408c6bf562988e",
    "city": "68b6bf0984408c6bf562988d",
    "address": "address-7ux8eiuf",
    "sharedWithTenants": [],
    "creator": "68c5bdd784408c6bf563bb9b",
    "tenant": "68c5bdd484408c6bf563bb87",
    "invoices": [],
    "transactions": [],
    "_id": "68c7d142289355d669c1a180",
    "deleted": false,
    "createdAt": "2025-09-15T08:41:38.938Z",
    "updatedAt": "2025-09-15T08:41:38.938Z",
    "__v": 0
  },
  {
    "isOther": false,
    "name": "acc-7rnzd68f",
    "phone": "09104457163",
    "phone2": "09374064003",
    "whatsapp": "09904167013",
    "brandName": "brand-z1on3pcr",
    "countTransactions": 0,
    "countInvoices": 0,
    "finalAmount": {},
    "finalShouldPay": {},
    "finalShouldReceive": {},
    "finalExchangeAmount": {},
    "finalExchangeShouldPay": {},
    "finalExchangeShouldReceive": {},
    "province": "68b6bf0984408c6bf562988e",
    "city": "68b6bf0984408c6bf562988d",
    "address": "address-3b8mtnmz",
    "sharedWithTenants": [],
    "creator": "68c5bdd784408c6bf563bb9b",
    "tenant": "68c5bdd484408c6bf563bb87",
    "invoices": [],
    "transactions": [],
    "_id": "68c7df01289355d669c1a303",
    "deleted": false,
    "createdAt": "2025-09-15T09:40:17.788Z",
    "updatedAt": "2025-09-15T09:40:17.788Z",
    "__v": 0
  },
  {
    "isOther": false,
    "name": "acc-wd3zmu3f",
    "phone": "09416780849",
    "phone2": "09157594339",
    "whatsapp": "09481836144",
    "brandName": "brand-hstuipw9",
    "countTransactions": 0,
    "countInvoices": 0,
    "finalAmount": {},
    "finalShouldPay": {},
    "finalShouldReceive": {},
    "finalExchangeAmount": {},
    "finalExchangeShouldPay": {},
    "finalExchangeShouldReceive": {},
    "province": "68b6bf0984408c6bf562988e",
    "city": "68b6bf0984408c6bf562988d",
    "address": "address-boxv5dgl",
    "sharedWithTenants": [],
    "creator": "68c5bdd784408c6bf563bb9b",
    "tenant": "68c5bdd484408c6bf563bb87",
    "invoices": [],
    "transactions": [],
    "_id": "68c7df26289355d669c1a450",
    "deleted": false,
    "createdAt": "2025-09-15T09:40:54.702Z",
    "updatedAt": "2025-09-15T09:40:54.702Z",
    "__v": 0
  },
  {
    "isOther": false,
    "name": "acc-ljliwiih",
    "phone": "09776265267",
    "phone2": "09819402244",
    "whatsapp": "09912075874",
    "brandName": "brand-k8wfdu49",
    "countTransactions": 0,
    "countInvoices": 0,
    "finalAmount": {},
    "finalShouldPay": {},
    "finalShouldReceive": {},
    "finalExchangeAmount": {},
    "finalExchangeShouldPay": {},
    "finalExchangeShouldReceive": {},
    "province": "68b6bf0984408c6bf562988e",
    "city": "68b6bf0984408c6bf562988d",
    "address": "address-x5bgn0ll",
    "sharedWithTenants": [],
    "creator": "68c5bdd784408c6bf563bb9b",
    "tenant": "68c5bdd484408c6bf563bb87",
    "invoices": [],
    "transactions": [],
    "_id": "68c7e011289355d669c1a5ac",
    "deleted": false,
    "createdAt": "2025-09-15T09:44:49.392Z",
    "updatedAt": "2025-09-15T09:44:49.392Z",
    "__v": 0
  },
  {
    "isOther": false,
    "name": "acc-5iz8uvdu",
    "phone": "09297324012",
    "phone2": "09215241891",
    "whatsapp": "09388189551",
    "brandName": "brand-bd7961p3",
    "countTransactions": 0,
    "countInvoices": 0,
    "finalAmount": {},
    "finalShouldPay": {},
    "finalShouldReceive": {},
    "finalExchangeAmount": {},
    "finalExchangeShouldPay": {},
    "finalExchangeShouldReceive": {},
    "province": "68b6bf0984408c6bf562988e",
    "city": "68b6bf0984408c6bf562988d",
    "address": "address-yyln8mwi",
    "sharedWithTenants": [],
    "creator": "68c5bdd784408c6bf563bb9b",
    "tenant": "68c5bdd484408c6bf563bb87",
    "invoices": [],
    "transactions": [],
    "_id": "68c7e050289355d669c1a747",
    "deleted": false,
    "createdAt": "2025-09-15T09:45:52.395Z",
    "updatedAt": "2025-09-15T09:45:52.395Z",
    "__v": 0
  },
  {
    "isOther": false,
    "name": "acc-39haa3gr",
    "phone": "09608840570",
    "phone2": "09644947004",
    "whatsapp": "09274099688",
    "brandName": "brand-1r88cq8z",
    "countTransactions": 0,
    "countInvoices": 0,
    "finalAmount": {},
    "finalShouldPay": {},
    "finalShouldReceive": {},
    "finalExchangeAmount": {},
    "finalExchangeShouldPay": {},
    "finalExchangeShouldReceive": {},
    "province": "68b6bf0984408c6bf562988e",
    "city": "68b6bf0984408c6bf562988d",
    "address": "address-qwvauskm",
    "sharedWithTenants": [],
    "creator": "68c5bdd784408c6bf563bb9b",
    "tenant": "68c5bdd484408c6bf563bb87",
    "invoices": [],
    "transactions": [],
    "_id": "68c7e0aa289355d669c1a898",
    "deleted": false,
    "createdAt": "2025-09-15T09:47:22.777Z",
    "updatedAt": "2025-09-15T09:47:22.777Z",
    "__v": 0
  },
  {
    "isOther": false,
    "name": "acc-j47bdb32",
    "phone": "09833968739",
    "phone2": "09632046419",
    "whatsapp": "09353147543",
    "brandName": "brand-0pfhxy7m",
    "countTransactions": 0,
    "countInvoices": 0,
    "finalAmount": {},
    "finalShouldPay": {},
    "finalShouldReceive": {},
    "finalExchangeAmount": {},
    "finalExchangeShouldPay": {},
    "finalExchangeShouldReceive": {},
    "province": "68b6bf0984408c6bf562988e",
    "city": "68b6bf0984408c6bf562988d",
    "address": "address-kwigdhdy",
    "sharedWithTenants": [],
    "creator": "68c5bdd784408c6bf563bb9b",
    "tenant": "68c5bdd484408c6bf563bb87",
    "invoices": [],
    "transactions": [],
    "_id": "68c7e178289355d669c1a9fd",
    "deleted": false,
    "createdAt": "2025-09-15T09:50:48.691Z",
    "updatedAt": "2025-09-15T09:50:48.691Z",
    "__v": 0
  },
  {
    "isOther": false,
    "name": "acc-2h9tcv6z",
    "phone": "09598724898",
    "phone2": "09574517016",
    "whatsapp": "09260865882",
    "brandName": "brand-kebh7xcg",
    "countTransactions": 0,
    "countInvoices": 0,
    "finalAmount": {},
    "finalShouldPay": {},
    "finalShouldReceive": {},
    "finalExchangeAmount": {},
    "finalExchangeShouldPay": {},
    "finalExchangeShouldReceive": {},
    "province": "68b6bf0984408c6bf562988e",
    "city": "68b6bf0984408c6bf562988d",
    "address": "address-h5tdd4xu",
    "sharedWithTenants": [],
    "creator": "68c5bdd784408c6bf563bb9b",
    "tenant": "68c5bdd484408c6bf563bb87",
    "invoices": [],
    "transactions": [],
    "_id": "68c7e1a4289355d669c1ab66",
    "deleted": false,
    "createdAt": "2025-09-15T09:51:32.510Z",
    "updatedAt": "2025-09-15T09:51:32.510Z",
    "__v": 0
  },
  {
    "isOther": false,
    "name": "acc-6vj5cgnc",
    "phone": "09517246817",
    "phone2": "09965229310",
    "whatsapp": "09268529244",
    "brandName": "brand-ibi4him6",
    "countTransactions": 0,
    "countInvoices": 0,
    "finalAmount": {},
    "finalShouldPay": {},
    "finalShouldReceive": {},
    "finalExchangeAmount": {},
    "finalExchangeShouldPay": {},
    "finalExchangeShouldReceive": {},
    "province": "68b6bf0984408c6bf562988e",
    "city": "68b6bf0984408c6bf562988d",
    "address": "address-5flyzs8d",
    "sharedWithTenants": [],
    "creator": "68c5bdd784408c6bf563bb9b",
    "tenant": "68c5bdd484408c6bf563bb87",
    "invoices": [],
    "transactions": [],
    "_id": "68c7e24d289355d669c1acc9",
    "deleted": false,
    "createdAt": "2025-09-15T09:54:21.604Z",
    "updatedAt": "2025-09-15T09:54:21.604Z",
    "__v": 0
  },
  {
    "isOther": false,
    "name": "acc-r1ldl16c",
    "phone": "09363981364",
    "phone2": "09268730279",
    "whatsapp": "09395647333",
    "brandName": "brand-y2iqy4c4",
    "countTransactions": 0,
    "countInvoices": 0,
    "finalAmount": {},
    "finalShouldPay": {},
    "finalShouldReceive": {},
    "finalExchangeAmount": {},
    "finalExchangeShouldPay": {},
    "finalExchangeShouldReceive": {},
    "province": "68b6bf0984408c6bf562988e",
    "city": "68b6bf0984408c6bf562988d",
    "address": "address-4fu0dv0r",
    "sharedWithTenants": [],
    "creator": "68c5bdd784408c6bf563bb9b",
    "tenant": "68c5bdd484408c6bf563bb87",
    "invoices": [],
    "transactions": [],
    "_id": "68c7e36a289355d669c1ae1a",
    "deleted": false,
    "createdAt": "2025-09-15T09:59:06.897Z",
    "updatedAt": "2025-09-15T09:59:06.897Z",
    "__v": 0
  },
  {
    "isOther": false,
    "name": "acc-yia85see",
    "phone": "09792530174",
    "phone2": "09730176183",
    "whatsapp": "09804382524",
    "brandName": "brand-nfi0jhvr",
    "countTransactions": 0,
    "countInvoices": 0,
    "finalAmount": {},
    "finalShouldPay": {},
    "finalShouldReceive": {},
    "finalExchangeAmount": {},
    "finalExchangeShouldPay": {},
    "finalExchangeShouldReceive": {},
    "province": "68b6bf0984408c6bf562988e",
    "city": "68b6bf0984408c6bf562988d",
    "address": "address-t41tc3hw",
    "sharedWithTenants": [],
    "creator": "68c5bdd784408c6bf563bb9b",
    "tenant": "68c5bdd484408c6bf563bb87",
    "invoices": [],
    "transactions": [],
    "_id": "68c7e3af289355d669c1af80",
    "deleted": false,
    "createdAt": "2025-09-15T10:00:15.298Z",
    "updatedAt": "2025-09-15T10:00:15.298Z",
    "__v": 0
  },
  {
    "isOther": false,
    "name": "acc-dgxed3pz",
    "phone": "09790971978",
    "phone2": "09651071070",
    "whatsapp": "09946583745",
    "brandName": "brand-2c5zxcej",
    "countTransactions": 0,
    "countInvoices": 0,
    "finalAmount": {},
    "finalShouldPay": {},
    "finalShouldReceive": {},
    "finalExchangeAmount": {},
    "finalExchangeShouldPay": {},
    "finalExchangeShouldReceive": {},
    "province": "68b6bf0984408c6bf562988e",
    "city": "68b6bf0984408c6bf562988d",
    "address": "address-z3c4cho2",
    "sharedWithTenants": [],
    "creator": "68c5bdd784408c6bf563bb9b",
    "tenant": "68c5bdd484408c6bf563bb87",
    "invoices": [],
    "transactions": [],
    "_id": "68c7e4e1289355d669c1b127",
    "deleted": false,
    "createdAt": "2025-09-15T10:05:21.772Z",
    "updatedAt": "2025-09-15T10:05:21.772Z",
    "__v": 0
  },
  {
    "isOther": false,
    "name": "acc-2dko9hes",
    "phone": "09212690013",
    "phone2": "09917632419",
    "whatsapp": "09353982499",
    "brandName": "brand-hsp7wj7z",
    "countTransactions": 0,
    "countInvoices": 0,
    "finalAmount": {},
    "finalShouldPay": {},
    "finalShouldReceive": {},
    "finalExchangeAmount": {},
    "finalExchangeShouldPay": {},
    "finalExchangeShouldReceive": {},
    "province": "68b6bf0984408c6bf562988e",
    "city": "68b6bf0984408c6bf562988d",
    "address": "address-5ii43gka",
    "sharedWithTenants": [],
    "creator": "68c5bdd784408c6bf563bb9b",
    "tenant": "68c5bdd484408c6bf563bb87",
    "invoices": [],
    "transactions": [],
    "_id": "68c7e5ca289355d669c1b282",
    "deleted": false,
    "createdAt": "2025-09-15T10:09:14.258Z",
    "updatedAt": "2025-09-15T10:09:14.258Z",
    "__v": 0
  },
  {
    "isOther": false,
    "name": "acc-sg4lf8x1",
    "phone": "09895468716",
    "phone2": "09453464087",
    "whatsapp": "09625153322",
    "brandName": "brand-fexco9ha",
    "countTransactions": 0,
    "countInvoices": 0,
    "finalAmount": {},
    "finalShouldPay": {},
    "finalShouldReceive": {},
    "finalExchangeAmount": {},
    "finalExchangeShouldPay": {},
    "finalExchangeShouldReceive": {},
    "province": "68b6bf0984408c6bf562988e",
    "city": "68b6bf0984408c6bf562988d",
    "address": "address-pfqdwg15",
    "sharedWithTenants": [],
    "creator": "68c5bdd784408c6bf563bb9b",
    "tenant": "68c5bdd484408c6bf563bb87",
    "invoices": [],
    "transactions": [],
    "_id": "68c7e77d289355d669c1b3f9",
    "deleted": false,
    "createdAt": "2025-09-15T10:16:29.736Z",
    "updatedAt": "2025-09-15T10:16:29.736Z",
    "__v": 0
  },
  {
    "isOther": false,
    "name": "acc-dczqht8t",
    "phone": "09989798782",
    "phone2": "09991279952",
    "whatsapp": "09341242588",
    "brandName": "brand-hzesw7lz",
    "countTransactions": 0,
    "countInvoices": 0,
    "finalAmount": {},
    "finalShouldPay": {},
    "finalShouldReceive": {},
    "finalExchangeAmount": {},
    "finalExchangeShouldPay": {},
    "finalExchangeShouldReceive": {},
    "province": "68b6bf0984408c6bf562988e",
    "city": "68b6bf0984408c6bf562988d",
    "address": "address-25afhiyl",
    "sharedWithTenants": [],
    "creator": "68c5bdd784408c6bf563bb9b",
    "tenant": "68c5bdd484408c6bf563bb87",
    "invoices": [],
    "transactions": [],
    "_id": "68c7e922289355d669c1b5cf",
    "deleted": false,
    "createdAt": "2025-09-15T10:23:30.457Z",
    "updatedAt": "2025-09-15T10:23:30.457Z",
    "__v": 0
  },
  {
    "isOther": false,
    "name": "acc-oqkn8bte",
    "phone": "09172449346",
    "phone2": "09749064262",
    "whatsapp": "09815747844",
    "brandName": "brand-nfjrt1lk",
    "countTransactions": 0,
    "countInvoices": 0,
    "finalAmount": {},
    "finalShouldPay": {},
    "finalShouldReceive": {},
    "finalExchangeAmount": {},
    "finalExchangeShouldPay": {},
    "finalExchangeShouldReceive": {},
    "province": "68b6bf0984408c6bf562988e",
    "city": "68b6bf0984408c6bf562988d",
    "address": "address-akc0m059",
    "sharedWithTenants": [],
    "creator": "68c5bdd784408c6bf563bb9b",
    "tenant": "68c5bdd484408c6bf563bb87",
    "invoices": [],
    "transactions": [],
    "_id": "68c7e9c7289355d669c1b6e2",
    "deleted": false,
    "createdAt": "2025-09-15T10:26:15.403Z",
    "updatedAt": "2025-09-15T10:26:15.403Z",
    "__v": 0
  },
  {
    "isOther": false,
    "name": "acc-5w3pth8l",
    "phone": "09721775219",
    "phone2": "09493048213",
    "whatsapp": "09100987760",
    "brandName": "brand-kpbl1zvl",
    "countTransactions": 0,
    "countInvoices": 0,
    "finalAmount": {},
    "finalShouldPay": {},
    "finalShouldReceive": {},
    "finalExchangeAmount": {},
    "finalExchangeShouldPay": {},
    "finalExchangeShouldReceive": {},
    "province": "68b6bf0984408c6bf562988e",
    "city": "68b6bf0984408c6bf562988d",
    "address": "address-bdmzwy27",
    "sharedWithTenants": [],
    "creator": "68c5bdd784408c6bf563bb9b",
    "tenant": "68c5bdd484408c6bf563bb87",
    "invoices": [],
    "transactions": [],
    "_id": "68c7ec95289355d669c1b8b5",
    "deleted": false,
    "createdAt": "2025-09-15T10:38:13.091Z",
    "updatedAt": "2025-09-15T10:38:13.091Z",
    "__v": 0
  },
  {
    "isOther": false,
    "name": "acc-vkdwyoyv",
    "phone": "09479974460",
    "phone2": "09368682794",
    "whatsapp": "09130978604",
    "brandName": "brand-tr4elw5c",
    "countTransactions": 0,
    "countInvoices": 0,
    "finalAmount": {},
    "finalShouldPay": {},
    "finalShouldReceive": {},
    "finalExchangeAmount": {},
    "finalExchangeShouldPay": {},
    "finalExchangeShouldReceive": {},
    "province": "68b6bf0984408c6bf562988e",
    "city": "68b6bf0984408c6bf562988d",
    "address": "address-jxgxk73a",
    "sharedWithTenants": [],
    "creator": "68c5bdd784408c6bf563bb9b",
    "tenant": "68c5bdd484408c6bf563bb87",
    "invoices": [],
    "transactions": [],
    "_id": "68c7ed79289355d669c1ba32",
    "deleted": false,
    "createdAt": "2025-09-15T10:42:01.281Z",
    "updatedAt": "2025-09-15T10:42:01.281Z",
    "__v": 0
  },
  {
    "isOther": false,
    "name": "acc-5k4nbpcl",
    "phone": "09500422684",
    "phone2": "09498745836",
    "whatsapp": "09612083781",
    "brandName": "brand-xmcasww9",
    "countTransactions": 0,
    "countInvoices": 0,
    "finalAmount": {},
    "finalShouldPay": {},
    "finalShouldReceive": {},
    "finalExchangeAmount": {},
    "finalExchangeShouldPay": {},
    "finalExchangeShouldReceive": {},
    "province": "68b6bf0984408c6bf562988e",
    "city": "68b6bf0984408c6bf562988d",
    "address": "address-efboi7hs",
    "sharedWithTenants": [],
    "creator": "68c5bdd784408c6bf563bb9b",
    "tenant": "68c5bdd484408c6bf563bb87",
    "invoices": [],
    "transactions": [],
    "_id": "68c7ed96289355d669c1bba2",
    "deleted": false,
    "createdAt": "2025-09-15T10:42:30.497Z",
    "updatedAt": "2025-09-15T10:42:30.497Z",
    "__v": 0
  }
]